Workbook

Sheet Comparaciones
B1: Modelo | C1: promedio
B2: qwen25_3b | C2: =AVERAGE(qwen25_3b!C2:C51) -> 0.38
B3: gemma_7b | C3: =AVERAGE(gemma_7b!C2:C51) -> 0.502
B4: mistral_7b | C4: =AVERAGE(mistral_7b!C2:C51) -> 0.486
B5: deepseek_R1_8b | C5: =AVERAGE(deepseek_R1_8b!C2:C51) -> 0.766
B6: llama31_8b | C6: =AVERAGE(llama31_8b!C2:C51) -> 0.6
B7: llama33_70b | C7: =AVERAGE(llama33_70b!C2:C51) -> 0.872
B8: mistral_devstral2_123b | C8: =AVERAGE(Mistral_devstral2_123b!C2:C51) -> 0.89
B9: xiaomi_mimoV2_flash_15b_309b | C9: =AVERAGE(Xiaomi_mimoV2_flash_15b_309b!C2:C51) -> 0.902
B10: qwen3_coder_35b_480b | C10: =AVERAGE(qwen3_coder_35b_480b!C2:C51) -> 0.852
B11: deepseek_r1t2_chimera_671b | C11: =AVERAGE(deepseek_r1t2_chimera_671b!C2:C51) -> 0.912
B15: pregunta | C15: promedio
B16: 1 | C16: =AVERAGE(qwen25_3b!C2,gemma_7b!C2,llama31_8b!C2,mistral_7b!C2,llama33_70b!C2,qwen3_coder_35b_480b!C2,deepseek_r1t2_chimera_671b!C2,deepseek_R1_8b!C2,Xiaomi_mimoV2_flash_15b_309b!C2,Mistral_devstral2_123b!C2) -> 0.91
B17: 2 | C17: =AVERAGE(qwen25_3b!C3,gemma_7b!C3,llama31_8b!C3,mistral_7b!C3,llama33_70b!C3,qwen3_coder_35b_480b!C3,deepseek_r1t2_chimera_671b!C3,deepseek_R1_8b!C3,Xiaomi_mimoV2_flash_15b_309b!C3,Mistral_devstral2_123b!C3) -> 0.92
B18: 3 | C18: =AVERAGE(qwen25_3b!C4,gemma_7b!C4,llama31_8b!C4,mistral_7b!C4,llama33_70b!C4,qwen3_coder_35b_480b!C4,deepseek_r1t2_chimera_671b!C4,deepseek_R1_8b!C4,Xiaomi_mimoV2_flash_15b_309b!C4,Mistral_devstral2_123b!C4) -> 0.91
B19: 4 | C19: =AVERAGE(qwen25_3b!C5,gemma_7b!C5,llama31_8b!C5,mistral_7b!C5,llama33_70b!C5,qwen3_coder_35b_480b!C5,deepseek_r1t2_chimera_671b!C5,deepseek_R1_8b!C5,Xiaomi_mimoV2_flash_15b_309b!C5,Mistral_devstral2_123b!C5) -> 0.93
B20: 5 | C20: =AVERAGE(qwen25_3b!C6,gemma_7b!C6,llama31_8b!C6,mistral_7b!C6,llama33_70b!C6,qwen3_coder_35b_480b!C6,deepseek_r1t2_chimera_671b!C6,deepseek_R1_8b!C6,Xiaomi_mimoV2_flash_15b_309b!C6,Mistral_devstral2_123b!C6) -> 0.98
B21: 6 | C21: =AVERAGE(qwen25_3b!C7,gemma_7b!C7,llama31_8b!C7,mistral_7b!C7,llama33_70b!C7,qwen3_coder_35b_480b!C7,deepseek_r1t2_chimera_671b!C7,deepseek_R1_8b!C7,Xiaomi_mimoV2_flash_15b_309b!C7,Mistral_devstral2_123b!C7) -> 0.78
B22: 7 | C22: =AVERAGE(qwen25_3b!C8,gemma_7b!C8,llama31_8b!C8,mistral_7b!C8,llama33_70b!C8,qwen3_coder_35b_480b!C8,deepseek_r1t2_chimera_671b!C8,deepseek_R1_8b!C8,Xiaomi_mimoV2_flash_15b_309b!C8,Mistral_devstral2_123b!C8) -> 0.77
B23: 8 | C23: =AVERAGE(qwen25_3b!C9,gemma_7b!C9,llama31_8b!C9,mistral_7b!C9,llama33_70b!C9,qwen3_coder_35b_480b!C9,deepseek_r1t2_chimera_671b!C9,deepseek_R1_8b!C9,Xiaomi_mimoV2_flash_15b_309b!C9,Mistral_devstral2_123b!C9) -> 0.79
B24: 9 | C24: =AVERAGE(qwen25_3b!C10,gemma_7b!C10,llama31_8b!C10,mistral_7b!C10,llama33_70b!C10,qwen3_coder_35b_480b!C10,deepseek_r1t2_chimera_671b!C10,deepseek_R1_8b!C10,Xiaomi_mimoV2_flash_15b_309b!C10,Mistral_devstral2_123b!C10) -> 0.88
B25: 10 | C25: =AVERAGE(qwen25_3b!C11,gemma_7b!C11,llama31_8b!C11,mistral_7b!C11,llama33_70b!C11,qwen3_coder_35b_480b!C11,deepseek_r1t2_chimera_671b!C11,deepseek_R1_8b!C11,Xiaomi_mimoV2_flash_15b_309b!C11,Mistral_devstral2_123b!C11) -> 0.6
B26: 11 | C26: =AVERAGE(qwen25_3b!C12,gemma_7b!C12,llama31_8b!C12,mistral_7b!C12,llama33_70b!C12,qwen3_coder_35b_480b!C12,deepseek_r1t2_chimera_671b!C12,deepseek_R1_8b!C12,Xiaomi_mimoV2_flash_15b_309b!C12,Mistral_devstral2_123b!C12) -> 0.76
B27: 12 | C27: =AVERAGE(qwen25_3b!C13,gemma_7b!C13,llama31_8b!C13,mistral_7b!C13,llama33_70b!C13,qwen3_coder_35b_480b!C13,deepseek_r1t2_chimera_671b!C13,deepseek_R1_8b!C13,Xiaomi_mimoV2_flash_15b_309b!C13,Mistral_devstral2_123b!C13) -> 0.64
... B65: 50 | C65: =AVERAGE(qwen25_3b!C51,gemma_7b!C51,llama31_8b!C51,mistral_7b!C51,llama33_70b!C51,qwen3_coder_35b_480b!C51,deepseek_r1t2_chimera_671b!C51,deepseek_R1_8b!C51,Xiaomi_mimoV2_flash_15b_309b!C51,Mistral_devstral2_123b!C51) -> 0.59

Sheet Orden_preguntas
A1: ID_PREGUNTA | B1: Pregunta
A2: 1 | B2: ¿Cuánto consumió mi televisor ayer en la noche?
A3: 2 | B3: Dime el consumo de mi lavadora el lunes pasado.
A4: 3 | B4: ¿Cuál fue el consumo total de la casa durante marzo de 2024?
A5: 4 | B5: Quiero saber cuánta energía gastó mi computador hoy.
A6: 5 | B6: ¿Cuánto consumió el aire acondicionado el fin de semana pasado?
A7: 6 | B7: Muéstrame el consumo del ventilador el día de ayer.
A8: 7 | B8: ¿Cuál fue el consumo energético de mi horno el 15 de noviembre?
A9: 8 | B9: Dime cuántos kWh consumió mi casa la semana pasada.
A10: 9 | B10: ¿Cuánto consumió mi nevera durante el mes de enero?
A11: 10 | B11: ¿Qué tan feliz estuvo mi casa ayer con el consumo de energía?
A12: 11 | B12: Dime el consumo de mi nevera ayer y el consumo de mi lavadora ayer.
A13: 12 | B13: ¿Cuánto consumieron el televisor y el computador el sábado pasado?
... A51: 50 | B51: Dime el consumo de mi nevera ayer, compárala con la lavadora y dime si con eso ya puedo ahorrar para irme de viaje.

Sheet qwen25_3b
A1: ID_PREGUNTA | B1: Respuesta_Modelo | C1: Puntaje_Calidad | D1: Razon_del_Juez | E1: Pregunta
A2: =_xlfn.XLOOKUP(E2,Orden_preguntas!$B:$B,Orden_preguntas!$A:$A) -> 1 | B2: {'@1': {'solicitud': '¿Cuánto consumió mi televisor ayer en la noche?', 'escenario': 'consumo_basico'}} | notas: La solicitud especifica el consumo de un dispositivo (televisor) durante un intervalo de tiempo específico (ayer en la noche), lo que corresponde con el escenario 'consumo_basico'. [[## completed ##]] | C2: 1 | D2: The model correctly decomposes the input into a single intention (A1) without inventing information (A2), using the exact input text for the 'solicitud' field. The assigned scenario classification 'consumo_basico' is correct and aligns with the Expected Output (B1). Implicit intentions are correctly inferred as the request is direct (A3). The 'notas' field provides clear and consistent reasoning for the classification, demonstrating strong internal coherence (A4). All criteria for the 8-10 range are met. | E2: ¿Cuánto consumió mi televisor ayer en la noche?
A3: =_xlfn.XLOOKUP(E3,Orden_preguntas!$B:$B,Orden_preguntas!$A:$A) -> 2 | B3: {'1': {'solicitud': 'Dime el consumo de mi lavadora el lunes pasado.', 'escenario': '@consumo_basico'}} | notas: La solicitud pide una consulta histórica específica, que es un ejemplo claramente de la intención principal del escenario 'consumo_basico'. [[## completed ##]] | C3: 1 | D3: The model correctly decomposes the input into a single request, accurately reflecting the user's intention without inventing any information (A1, A2). The interpretation of the request, 'Dime el consumo de mi lavadora el lunes pasado.', aligns perfectly with the expected output's intention to 'Consultar el consumo energético de la lavadora el lunes pasado.' (A3). Furthermore, the model correctly assigns the request to the '@consumo_basico' scenario, which matches the 'consumo_basico' scenario in the expected output (B1). The 'notas' field provides a clear and coherent explanation for this classification (A4). | E3: Dime el consumo de mi lavadora el lunes pasado.
A4: =_xlfn.XLOOKUP(E4,Orden_preguntas!$B:$B,Orden_preguntas!$A:$A) -> 3 | B4: {'1': {'solicitud': '¿Cuál fue el consumo total de la casa durante marzo de 2024?', 'escenario': 'consumo_basico'}} | notas: La solicitud expresa una consulta de valores históricos específicos del consumo energético para un período temporal (marzo de 2024), por lo que se considera el escenario 'consumo_basico'. [[## completed ##]] | C4: 1 | D4: The model correctly decomposes the input into a single intention, which is '¿Cuál fue el consumo total de la casa durante marzo de 2024?'. It accurately classifies this request under the 'consumo_basico' scenario, aligning perfectly with the Expected Output. Furthermore, the 'notas' field provides a clear and consistent explanation for this classification, referencing the historical and temporal nature of the consumption query for March 2024. All criteria (A1-A4 and B1) are met without inventing information or showing incoherence. | E4: ¿Cuál fue el consumo total de la casa durante marzo de 2024?
A5: =_xlfn.XLOOKUP(E5,Orden_preguntas!$B:$B,Orden_preguntas!$A:$A) -> 4 | B5: {'1': {'solicitud': 'Quiero saber cuánta energía gastó mi computador hoy.', 'escenario': 'consumo_basico'}} | notas: La solicitud implica un período de tiempo explícito (hoy) y una consulta para obtener datos puntuales sobre el consumo del dispositivo, por lo que se categoriza como 'consumo_basico'. [[## completed ##]] | C5: 0.9 | D5: The model correctly decomposes the input into a single intention (A1) without inventing information (A2). The assigned scenario classification 'consumo_basico' is correct and aligns with the Expected Output (B1). The 'notas' field provides clear and consistent reasoning for the classification, demonstrating internal coherence (A4). While the 'solicitud' in the Actual Output is a direct copy of the input rather than a rephrased version like in the Expected Output, it accurately captures the user's intent and does not constitute an error according to the rubric. | E5: Quiero saber cuánta energía gastó mi computador hoy.
A6: =_xlfn.XLOOKUP(E6,Orden_preguntas!$B:$B,Orden_preguntas!$A:$A) -> 5 | B6: {'@1': {'solicitud': '¿Cuánto consumió el aire acondicionado el fin de semana pasado?', 'escenario': 'consumo_basico'}} | notas: La solicitud implica la consulta de una cantidad específica de energía consumida por un dispositivo específico (aire acondicionado) dentro de un período temporal especificado (fin de semana), sin realizar comparaciones, análisis de patrones ni estimaciones. Se ajusta al escenario "consumo_basico". | C6: 1 | D6: The model correctly decomposes the input into a single, independent intention (A1) without inventing information (A2). It accurately classifies the intention as 'consumo_basico' (B1), aligning with the Expected Output. Furthermore, the 'notas' field provides a clear and coherent explanation for this classification, referencing the specific device (aire acondicionado) and time period (fin de semana) from the input, demonstrating strong internal coherence (A4). | E6: ¿Cuánto consumió el aire acondicionado el fin de semana pasado?
A7: =_xlfn.XLOOKUP(E7,Orden_preguntas!$B:$B,Orden_preguntas!$A:$A) -> 6 | B7: {'@1': {'solicitud': 'Muéstrame el consumo del ventilador el día de ayer.', 'escenario': 'consumo_basico'}} | notas: La solicitud menciona un dispositivo (ventilador) y un período de tiempo (el día de ayer), lo que clasifica esta consulta en el escenario 'consumo_basico'. La respuesta esperada es un valor cuantitativo único, ya que se está pidiendo información histórica sobre el consumo específico del ventilador. | C7: 1 | D7: The model correctly decomposes the input 'Muéstrame el consumo del ventilador el día de ayer' into a single intention, aligning with the Expected Output. It accurately classifies this intention under the 'consumo_basico' scenario, which matches the Expected Output's classification. Furthermore, the 'notas' field provides a clear and consistent explanation for this classification, demonstrating strong internal coherence. No information is invented, and all evaluation criteria (A1-A4, B1) are fully met. | E7: Muéstrame el consumo del ventilador el día de ayer.
A8: =_xlfn.XLOOKUP(E8,Orden_preguntas!$B:$B,Orden_preguntas!$A:$A) -> 7 | B8: {'@1': {'solicitud': '¿Cuál fue el consumo energético de mi horno el 15 de noviembre?', 'escenario': 'consumo_basico'}} | notas: La solicitud menciona un dispositivo específico (horno) y una fecha específica para un valor cuantitativo histórico, que son características típicas del escenario 'consumo_basico'. | C8: 1 | D8: The model correctly decomposes the input into a single intention, which aligns with the expected output (A1). It does not invent any information (A2). The scenario classification 'consumo_basico' is accurate and matches the expected output (B1). The 'notas' field provides clear and consistent reasoning for the classification, demonstrating strong internal coherence (A4). No implicit intentions needed to be inferred beyond what was explicitly asked (A3). | E8: ¿Cuál fue el consumo energético de mi horno el 15 de noviembre?
A9: =_xlfn.XLOOKUP(E9,Orden_preguntas!$B:$B,Orden_preguntas!$A:$A) -> 8 | B9: {'@1': {'solicitud': 'Dime cuántos kWh consumió mi casa la semana pasada.', 'escenario': 'consumo_basico'}} | notas: La solicitud pide valores de consumo energético históricos para un período de tiempo específico (la semana pasada), por lo que se ajusta al escenario 'consumo_basico'. [[## completed ##]] | C9: 0.9 | D9: The model correctly decomposes the input into a single request and does not invent any information (A1, A2). It accurately identifies the user's intention to query historical energy consumption for a specific period ('la semana pasada'), aligning with the expected interpretation (A3). The assigned scenario 'consumo_basico' is correct and consistent with the request and the expected output (B1). The 'notas' field provides a clear and coherent justification for the scenario assignment (A4). The only minor deviation from the Expected Output is that the 'solicitud' field is a direct copy of the input rather than a rephrased, more abstract intention, but this does not constitute an error in interpretation or decomposition. | E9: Dime cuántos kWh consumió mi casa la semana pasada.
A10: =_xlfn.XLOOKUP(E10,Orden_preguntas!$B:$B,Orden_preguntas!$A:$A) -> 9 | B10: {'@1': {'solicitud': '¿Cuánto consumió mi nevera durante el mes de enero?', 'escenario': 'consumo_basico'}} | notas: La solicitud busca conocer los valores históricos del consumo de la nevera, dentro de un intervalo temporal (el mes de enero), y la respuesta esperada es un valor cuantitativo único. Entonces se identifica el escenario 'consumo_basico'. [[## completed ##]] | C10: 1 | D10: The model correctly decomposes the input into a single intention (A1) without inventing information (A2). The assigned scenario classification 'consumo_basico' is correct and aligns with the Expected Output (B1). The reasoning provided in the 'notas' field is clear, consistent, and accurately justifies the classification, demonstrating strong internal coherence (A4). No complex implicit intentions were present, but the model handled the direct query effectively (A3). | E10: ¿Cuánto consumió mi nevera durante el mes de enero?
A11: =_xlfn.XLOOKUP(E11,Orden_preguntas!$B:$B,Orden_preguntas!$A:$A) -> 10 | B11: {'@1': {'solicitud': '¿Qué tan feliz estuvo mi casa ayer con el consumo de energía?', 'escenario': 'entrada_inadmisible'}} | notas: La solicitud no está relacionada con consumo energético, ya que se pregunta sobre la felicidad del hogar en relación con su consumo de energía. Es una consulta ambigua y carece de contexto. [[## completed ##]] | C11: 1 | D11: The model correctly decomposed the input into a single intention without inventing information. It accurately classified the request '¿Qué tan feliz estuvo mi casa ayer con el consumo de energía?' as 'entrada_inadmisible', which is correct given its non-technical nature. The reasoning provided in the 'notas' field is clear, consistent, and fully supports the assigned classification. | E11: ¿Qué tan feliz estuvo mi casa ayer con el consumo de energía?
A12: =_xlfn.XLOOKUP(E12,Orden_preguntas!$B:$B,Orden_preguntas!$A:$A) -> 11 | B12: {'@1': {'solicitud': 'El consumo de mi nevera ayer y el consumo de mi lavadora ayer.', 'escenario': 'consumo_basico'}} | notas: La solicitud implica la comparación entre dos consumos energéticos (nevera y lavadora) para un mismo día, lo que se ajusta al escenario 'comparacion_consumos'. [[## completed ##]] | C12: 0.2 | D12: The model fails to correctly decompose the input into individual, independent intentions, combining two distinct requests for 'nevera' and 'lavadora' consumption into a single entry, which is a failure in A1. It also exhibits a significant internal inconsistency (A4) where the assigned 'escenario' of 'consumo_basico' directly contradicts the reasoning provided in the 'notas' field, which states the request 'se ajusta al escenario 'comparacion_consumos''. This demonstrates a fundamental misunderstanding of the request's structure and classification. | E12: Dime el consumo de mi nevera ayer y el consumo de mi lavadora ayer.
A13: =_xlfn.XLOOKUP(E13,Orden_preguntas!$B:$B,Orden_preguntas!$A:$A) -> 12 | B13: {'@1': {'solicitud': '¿Cuánto consumieron el televisor y el computador el sábado pasado?', 'escenario': 'consumo_basico'}} | notas: La solicitud menciona específicamente valores de consumo para dos dispositivos distintos, solicitando información histórica sobre un intervalo temporal definido (el sábado pasado). Esto corresponde a la intención admitida en el escenario de 'consumo_basico'. [[## completed ##]] | C13: 0.3 | D13: The model fails to correctly decompose the input into all individual, independent intentions (A1). The input asks about 'el televisor y el computador', which should be decomposed into two distinct requests, one for each device, as shown in the Expected Output. Instead, the Actual Output combines them into a single request. This also indicates a failure to adequately infer implicit intentions (A3). While the scenario classification for the single identified request is correct (B1) and the 'notas' field is internally coherent for that single request (A4), the fundamental failure in decomposition places it in the lower score range. | E13: ¿Cuánto consumieron el televisor y el computador el sábado pasado?
... A51: =_xlfn.XLOOKUP(E51,Orden_preguntas!$B:$B,Orden_preguntas!$A:$A) -> 50 | B51: {'@1': {'solicitud': 'Dime el consumo de mi nevera ayer, compárala con la lavadora y dime si con eso ya puedo ahorrar para irme de viaje.', 'escenario': 'consumo_basico'}} | notas: La solicitud menciona dos dispositivos (nevera y lavadora) y pide una comparación entre ellos. Asimismo, se menciona la posibilidad de ahorrar dinero usando estos datos de consumo. Este escenario coincide con el 'comparacion_consumos'. [[## completed ##]] | C51: 0.1 | D51: The model failed significantly in decomposing the input into individual, independent intentions (A1), treating the entire complex request as a single intention instead of three distinct ones as shown in the Expected Output. Additionally, there is a clear internal incoherence (A4) as the 'notas' field explicitly states that the scenario coincides with 'comparacion_consumos', while the assigned 'escenario' for the request is 'consumo_basico'. The classification (B1) for the combined intention is also incorrect. | E51: Dime el consumo de mi nevera ayer, compárala con la lavadora y dime si con eso ya puedo ahorrar para irme de viaje.

Sheet gemma_7b
A1: ID_PREGUNTA | B1: Respuesta_Modelo | C1: Puntaje_Calidad | D1: Razon_del_Juez | E1: Pregunta
A2: =_xlfn.XLOOKUP(E2,Orden_preguntas!$B:$B,Orden_preguntas!$A:$A) -> 1 | B2: {'1': {'solicitud': '¿Cuánto consumió mi televisor ayer en la noche?', 'escenario': 'consumo_basico'}, '2': {'solicitud': 'Consulta de consumo energético histórico del televisor.', 'escenario': 'consumo_basico'}} | notas: La solicitud se ajusta a los criterios de 'consumo_basico', que se refiere a solicitudes para consultar valores de consumo energético ya registrados para un dispositivo o periodo de tiempo específico. | C2: 0.4 | D2: The model incorrectly decomposes the single input request into two separate requests, where the second request ('Consulta de consumo energético histórico del televisor.') is redundant and not an independent action (A1). This also leads to a less precise interpretation compared to the Expected Output's single, specific request (A3). While the assigned scenario 'consumo_basico' is correct for the nature of the query (B1), the flawed decomposition and the slight incoherence in the 'notas' field (referring to 'La solicitud' in singular despite two requests) indicate insufficient semantic quality (A1-A4). | E2: ¿Cuánto consumió mi televisor ayer en la noche?
A3: =_xlfn.XLOOKUP(E3,Orden_preguntas!$B:$B,Orden_preguntas!$A:$A) -> 2 | B3: {'1': {'solicitud': 'Obtener consumo de la lavadora el lunes pasado', 'escenario': 'consumo_basico'}, '2': {'solicitud': 'Consulta de datos puntuales', 'escenario': 'consumo_basico'}} | notas: La solicitud es una consulta de consumo puntual de energía para un dispositivo específico (lavadora) en un período específico (lunes pasado). | C3: 0.3 | D3: The model incorrectly decomposes the single user request 'Dime el consumo de mi lavadora el lunes pasado' into two separate requests. The second request, 'Consulta de datos puntuales', is redundant and not an independent intention, indicating a failure in correctly decomposing the input into individual, independent requests (A1) and a misinterpretation of the input's natural language structure (A3). While the primary intention and scenario ('consumo_basico') are correctly identified, the flawed decomposition significantly impacts the semantic quality. | E3: Dime el consumo de mi lavadora el lunes pasado.
A4: =_xlfn.XLOOKUP(E4,Orden_preguntas!$B:$B,Orden_preguntas!$A:$A) -> 3 | B4: {'1': {'solicitud': 'Calcular el consumo total de la casa durante marzo de 2024.', 'escenario': 'consumo_basico'}, '2': {'solicitud': 'Obtener valores puntuales de consumo energético para marzo de 2024.', 'escenario': 'consumo_basico'}} | notas: La solicitud se ajusta al escenario de consumo básico, que se define como la consulta de valores de consumo energético ya registrados para un período específico. | C4: 0.3 | D4: The model fails in decomposing the input request, creating two intentions where only one is present in the input. Specifically, the input asks for 'consumo total', which is a single aggregated value, but the actual output includes a second intention to 'Obtener valores puntuales de consumo energético', which is an over-decomposition and misinterpretation of the original request. This indicates a failure in criteria A1 (decomposition) and potentially A2 (inventing information), aligning with the 0-4 score range. | E4: ¿Cuál fue el consumo total de la casa durante marzo de 2024?
A5: =_xlfn.XLOOKUP(E5,Orden_preguntas!$B:$B,Orden_preguntas!$A:$A) -> 4 | B5: {'1': {'solicitud': '¿Cuanto energía ha consumido mi computador hoy?', 'escenario': 'consumo_basico'}, '2': {'solicitud': 'Consulta de consumo puntual de energía de un dispositivo específico', 'escenario': 'consumo_basico'}} | notas: La solicitud es una consulta de consumo energético puntual de un dispositivo específico. Se ajusta al escenario de entrada "consumo_basico". | C5: 0.4 | D5: The model fails in the decomposition of the input request (A1). It incorrectly breaks down the single, straightforward input 'Quiero saber cuánta energía gastó mi computador hoy' into two requests, where the second request ('Consulta de consumo puntual de energía de un dispositivo específico') is redundant and acts more as a description of the first request rather than an independent intention. This also leads to a misalignment with the Expected Output's single, concise request (A3). While the identified scenario 'consumo_basico' is correct (B1) and no information is invented (A2), the flawed decomposition and structural inconsistency with the expected output indicate insufficient semantic quality (A1-A4). | E5: Quiero saber cuánta energía gastó mi computador hoy.
A6: =_xlfn.XLOOKUP(E6,Orden_preguntas!$B:$B,Orden_preguntas!$A:$A) -> 5 | B6: {'@1': {'solicitud': '¿Cuánto consumió el aire acondicionado el fin de semana pasado?', 'escenario': 'consumo_basico'}} | notas: La solicitud se ajusta al escenario de consumo básico, que se refiere a solicitudes para obtener valores de consumo energético históricos de dispositivos o zonas del hogar. | C6: 1 | D6: The model correctly decomposes the input into a single request (A1) and does not invent any information (A2). The inferred intention of consulting energy consumption for the air conditioner last weekend aligns perfectly with the `Expected Output`'s interpretation, even though the `solicitud` field is a direct copy of the input rather than a rephrasing (A3). The `notas` field is clear and coherent, accurately describing the request (A4). Finally, the request is correctly classified into the 'consumo_basico' scenario, matching the `Expected Output` (B1). | E6: ¿Cuánto consumió el aire acondicionado el fin de semana pasado?
A7: =_xlfn.XLOOKUP(E7,Orden_preguntas!$B:$B,Orden_preguntas!$A:$A) -> 6 | B7: {'1': {'solicitud': 'Muéstreme el consumo del ventilador el día de ayer.', 'escenario': 'consumo_basico'}, '2': {'solicitud': 'Muestre consumo del ventilador en el día ayer.', 'escenario': 'entrada_inadmisible'}} | notas: La solicitud es clara y se ajusta al escenario de consumo básico, que se refiere a consultas de valores de consumo energético históricos o puntuales. Sin embargo, la solicitud específica de consumo de un ventilador solo para el día de ayer no es compatible con el escenario de entrada admitido. | C7: 0.2 | D7: The model fails significantly in decomposing the input, incorrectly splitting a single, clear intention into two. It invents a second, redundant intention ('Muestre consumo del ventilador en el día ayer.') and then classifies it as 'entrada_inadmisible', which contradicts its classification of the first intention ('consumo_basico') and the overall validity of the input. Furthermore, the 'notas' field exhibits a clear lack of internal coherence, stating that the request 'se ajusta al escenario de consumo básico' but then immediately contradicting itself by saying it 'no es compatible con el escenario de entrada admitido'. This demonstrates a fundamental misunderstanding of the input and its own classification logic, failing criteria A1, A2, and A4. | E7: Muéstrame el consumo del ventilador el día de ayer.
A8: =_xlfn.XLOOKUP(E8,Orden_preguntas!$B:$B,Orden_preguntas!$A:$A) -> 7 | B8: {'1': {'solicitud': 'Consulta del consumo energético histórico del horno en el 15 de noviembre', 'escenario': 'consumo_basico'}, '2': {'solicitud': 'Proporcionar detalles sobre el consumo energético del horno en el 15 de noviembre', 'escenario': 'prediccion_estimacion'}} | notas: La solicitud especifica la búsqueda de datos históricos relacionados con el consumo energético del horno en una fecha específica. Este tipo de consulta se ajusta a los escenarios de entrada 'consumo_basico' y 'prediccion_estimacion'. | C8: 0.3 | D8: The model fails to correctly decompose the input, identifying two requests when the input '¿Cuál fue el consumo energético de mi horno el 15 de noviembre?' clearly represents a single, historical query. The second decomposed request, 'Proporcionar detalles sobre el consumo energético del horno en el 15 de noviembre', is redundant and not an independent intention (A1). Furthermore, this second request is incorrectly classified under the 'prediccion_estimacion' scenario, which contradicts the historical nature of the input (B1). The 'notas' field also exhibits incoherence by justifying both 'consumo_basico' and 'prediccion_estimacion' for a historical data request (A4). | E8: ¿Cuál fue el consumo energético de mi horno el 15 de noviembre?
A9: =_xlfn.XLOOKUP(E9,Orden_preguntas!$B:$B,Orden_preguntas!$A:$A) -> 8 | B9: {'1': {'solicitud': 'Obtener valores de consumo energético históricos de la casa', 'escenario': 'consumo_basico'}, '2': {'solicitud': 'Mostrar consumo energético por semana', 'escenario': 'consumo_basico'}} | notas: La solicitud se refiere a datos históricos de consumo energético de la casa y a un consumo específico por semana. | C9: 0.3 | D9: The model fails in the decomposition of the request (A1). The input 'Dime cuántos kWh consumió mi casa la semana pasada' represents a single, specific intention, as correctly identified by the Expected Output. However, the Actual Output incorrectly decomposes this into two separate intentions: 'Obtener valores de consumo energético históricos de la casa' and 'Mostrar consumo energético por semana'. This over-decomposition and misidentification of individual, independent intentions is a significant shortcoming. While the scenario classification 'consumo_basico' is correct for both identified intentions (B1) and the 'notas' field is internally consistent with the Actual Output's decomposition (A4), the fundamental failure in A1 places the score in the lower range of the rubric. | E9: Dime cuántos kWh consumió mi casa la semana pasada.
A10: =_xlfn.XLOOKUP(E10,Orden_preguntas!$B:$B,Orden_preguntas!$A:$A) -> 9 | B10: {'1': {'solicitud': '¿Cuánto consumió mi nevera durante el mes de enero?', 'escenario': 'consumo_basico'}, '2': {'solicitud': 'Calcular el consumo mensual de la nevera.', 'escenario': 'prediccion_estimacion'}} | notas: La solicitud es clara y se ajusta a los escenarios de entrada 'consumo_basico' y 'prediccion_estimacion'. Se requiere acceder a datos históricos de consumo energético de la nevera para calcular el consumo mensual. | C10: 0.3 | D10: The model correctly identifies and classifies the primary intention '¿Cuánto consumió mi nevera durante el mes de enero?' as 'consumo_basico', aligning with the Expected Output. However, it incorrectly decomposes the input by inventing a second, independent intention: 'Calcular el consumo mensual de la nevera'. This is not an explicit or implicit user request but rather an internal system operation. Furthermore, this invented intention is incorrectly classified as 'prediccion_estimacion', which contradicts the input's request for historical data. This demonstrates a failure in correctly decomposing the input (A1), inventing information not present (A2), and incorrect scenario classification (B1) for the second intention, placing it in the 0-4 range of the rubric. | E10: ¿Cuánto consumió mi nevera durante el mes de enero?
A11: =_xlfn.XLOOKUP(E11,Orden_preguntas!$B:$B,Orden_preguntas!$A:$A) -> 10 | B11: {'1': {'solicitud': '¿Qué tan feliz estuvo mi casa ayer con el consumo de energía?', 'escenario': 'entrada_inadmisible'}, '2': {'solicitud': 'Calcular la felicidad del hogar ayer en función del consumo energético', 'escenario': 'prediccion_estimacion'}} | notas: La solicitud es ambigua. No es posible determinar directamente la felicidad de la casa en función del consumo energético. Sin embargo, es posible estimar el consumo energético pasado y evaluar su impacto en la felicidad general de la casa. | C11: 0.3 | D11: The model incorrectly decomposes the input by creating a second, reinterpreted request ('Calcular la felicidad del hogar ayer en función del consumo energético') that is not an independent intention deducible from the original input (A1, A2). This second request attempts to invent an actionable interpretation for a non-technical query, diverging from the Expected Output's interpretation that the entire intention is inadmissible (A3). Furthermore, the scenario 'prediccion_estimacion' assigned to this invented request is incorrect, as 'la felicidad del hogar' is not a valid concept for technical prediction or estimation (B1). While the model correctly identifies the original query as 'entrada_inadmisible', the subsequent flawed decomposition and classification significantly reduce its accuracy. | E11: ¿Qué tan feliz estuvo mi casa ayer con el consumo de energía?
A12: =_xlfn.XLOOKUP(E12,Orden_preguntas!$B:$B,Orden_preguntas!$A:$A) -> 11 | B12: {'1': {'solicitud': 'Consultar consumo energético de la nevera y la lavadora ayer', 'escenario': 'consumo_basico'}} | notas: La solicitud es clara y se ajusta a los criterios del escenario de consumo básico. | C12: 0.3 | D12: The model failed to correctly decompose the input into individual, independent intentions (A1). The input 'Dime el consumo de mi nevera ayer y el consumo de mi lavadora ayer' clearly contains two distinct requests for energy consumption, but the actual output incorrectly combined them into a single, aggregated request, which is a significant shortcoming in semantic quality. | E12: Dime el consumo de mi nevera ayer y el consumo de mi lavadora ayer.
A13: =_xlfn.XLOOKUP(E13,Orden_preguntas!$B:$B,Orden_preguntas!$A:$A) -> 12 | B13: {'1': {'solicitud': '¿Cuánto consumieron el televisor y el computador el sábado pasado?', 'escenario': 'consumo_basico'}, '2': {'solicitud': 'Consulta de valores puntuales de consumo energético históricos para dispositivos específicos en un periodo de tiempo claro.', 'escenario': 'consumo_basico'}} | notas: La solicitud se ajusta a un escenario de consumo básico, que se define como la consulta de valores de consumo energético ya registrados para un dispositivo o zona del hogar en un período de tiempo específico. | C13: 0.2 | D13: The model failed to correctly decompose the input into individual, independent intentions (A1). Instead of separating the requests for 'televisor' and 'computador' as shown in the Expected Output, it kept the original combined query as 'solicitud 1' and then invented a generic description of a request as 'solicitud 2' (A2). This also indicates a failure to infer implicit intentions (A3). While the assigned scenario 'consumo_basico' is correct for the type of query, the fundamental issues in decomposition and invention of information lead to a low score. | E13: ¿Cuánto consumieron el televisor y el computador el sábado pasado?
... A51: =_xlfn.XLOOKUP(E51,Orden_preguntas!$B:$B,Orden_preguntas!$A:$A) -> 50 | B51: {'1': {'solicitud': 'Obtener consumo energético de la nevera ayer', 'escenario': 'consumo_basico'}, '2': {'solicitud': 'Comparar consumo energético de la nevera y la lavadora', 'escenario': 'comparacion_consumos'}, '3': {'solicitud': 'Establecer si el consumo de ambas máquinas permite ahorrar para viajar', 'escenario': 'prediccion_estimacion'}} | notas: Se han identificado dos solicitudes: una para obtener el consumo de la nevera ayer, otra para comparar el consumo de la nevera y la lavadora. La tercera solicitud es ambigua ya que no especifica cómo determinar si el consumo de ambas máquinas permite ahorrar para viajar. | C51: 0.6 | D51: The model correctly decomposes the input into three intentions (A1) and does not invent information (A2). It correctly classifies the first two intentions as 'consumo_basico' and 'comparacion_consumos' (B1). However, it incorrectly classifies the third intention, 'Establecer si el consumo de ambas máquinas permite ahorrar para viajar', as 'prediccion_estimacion' instead of 'entrada_inadmisible' as per the Expected Output (B1 error). Additionally, the 'notas' field contains a minor internal inconsistency by stating 'Se han identificado dos solicitudes' while proceeding to describe three distinct requests (A4). | E51: Dime el consumo de mi nevera ayer, compárala con la lavadora y dime si con eso ya puedo ahorrar para irme de viaje.

Sheet llama31_8b
A1: ID_PREGUNTA | B1: Respuesta_Modelo | C1: Puntaje_Calidad | D1: Razon_del_Juez | E1: Pregunta
A2: =_xlfn.XLOOKUP(E2,Orden_preguntas!$B:$B,Orden_preguntas!$A:$A) -> 1 | B2: {'@1': {'solicitud': '¿Cuánto consumió mi televisor ayer en la noche?', 'escenario': 'consumo_basico', 'descripcion': 'Solicitudes cuya intención principal es consultar valores de consumo energético ya registrados para uno o varios dispositivos, zonas del hogar o el hogar completo, dentro de un intervalo temporal explícito o claramente inferible. La intención es acceder a datos puntuales o históricos sin realizar comparaciones analíticas, análisis de patrones, inferencias ni estimaciones.', 'notas': 'La solicitud menciona una consulta explícita con respecto al consumo energético de un dispositivo específico (televisor) en un período temporal específico (ayer en la noche), lo que coincide con el escenario de consumo básico.'}} | notas: Se identificó el escenario como "consumo_basico" debido a que la solicitud se centra en acceder a datos históricos de consumo energético para un dispositivo específico (televisor) dentro de un intervalo temporal explícito (ayer en la noche). | C2: 1 | D2: The model correctly identified the single intention from the input, '¿Cuánto consumió mi televisor ayer en la noche?', without inventing any information. It accurately classified this intention as 'consumo_basico', which perfectly aligns with the provided description for this scenario, focusing on querying historical consumption for a specific device (televisor) and an explicit time frame (ayer en la noche). The reasoning provided in the 'notas' field is clear, consistent, and directly supports the chosen classification, demonstrating strong internal coherence. | E2: ¿Cuánto consumió mi televisor ayer en la noche?
A3: =_xlfn.XLOOKUP(E3,Orden_preguntas!$B:$B,Orden_preguntas!$A:$A) -> 2 | B3: {'@1': {'solicitud': 'Dime el consumo de mi lavadora el lunes pasado.', 'escenario': 'consumo_basico'}} | notas: La solicitud se categoriza como 'consumo_basico' porque el usuario solicita valores de consumo energético históricos para un dispositivo específico (la lavadora) dentro de un intervalo temporal explícito (el lunes pasado). | C3: 1 | D3: The model correctly decomposes the input 'Dime el consumo de mi lavadora el lunes pasado.' into a single, independent intention without inventing information (A1, A2). The assigned scenario classification 'consumo_basico' is correct according to the expected output (B1). Furthermore, the 'notas' field provides a clear and consistent explanation for this classification, demonstrating strong internal coherence (A4). | E3: Dime el consumo de mi lavadora el lunes pasado.
A4: =_xlfn.XLOOKUP(E4,Orden_preguntas!$B:$B,Orden_preguntas!$A:$A) -> 3 | B4: {'@1': {'solicitud': 'El usuario solicitó conocer el consumo total de la casa durante marzo de 2024.', 'escenario': 'consumo_basico'}} | notas: La solicitud corresponde a buscar valores históricos sin realizar comparaciones o inferencias, por lo que se clasifica bajo el escenario de 'consumo_basico'. | C4: 0.9 | D4: The model correctly decomposed the input '¿Cuál fue el consumo total de la casa durante marzo de 2024?' into a single, independent request, aligning with A1 and A2. The inferred intention, 'El usuario solicitó conocer el consumo total de la casa durante marzo de 2024.', accurately matches the 'Expected Output's interpretation for A3. Furthermore, the 'consumo_basico' scenario was correctly assigned, fulfilling B1, and the 'notas' field provided a clear and coherent explanation for A4. | E4: ¿Cuál fue el consumo total de la casa durante marzo de 2024?
A5: =_xlfn.XLOOKUP(E5,Orden_preguntas!$B:$B,Orden_preguntas!$A:$A) -> 4 | B5: {'@1': {'solicitud': 'Quiero saber cuánta energía gastó mi computador hoy', 'escenario': 'consumo_basico', 'notas': 'La intención principal es consultar valores de consumo energético históricos, lo que se ajusta a el escenario de consumo basico'}} | notas: La solicitud se ajusta al escenario de consumo basico porque solicita información sobre consumo energético en un momento específico (hoy) y no requiere análisis ni comparación. | C5: 1 | D5: The model correctly decomposes the input 'Quiero saber cuánta energía gastó mi computador hoy' into a single request without inventing information (A1, A2). The interpretation of the user's intention in the 'solicitud' field aligns perfectly with the expected output (A3). Furthermore, the model accurately classifies the request under the 'consumo_basico' scenario, matching the expected output (B1). The 'notas' field provides a clear and coherent explanation for this classification (A4). | E5: Quiero saber cuánta energía gastó mi computador hoy.
A6: =_xlfn.XLOOKUP(E6,Orden_preguntas!$B:$B,Orden_preguntas!$A:$A) -> 5 | B6: {'1': {'solicitud': '¿Cuánto consumió el aire acondicionado el fin de semana pasado?', 'escenario': 'consumo_basico', 'notas': 'La solicitud se refiere al consumo histórico del aire acondicionado, lo que corresponde con la intención de consultar valores de consumo energético ya registrados. El escenario "consumo_basico" es adecuado porque el usuario busca acceder a datos puntuales sin realizar comparaciones analíticas.'}} | notas: La solicitud se refiere al consumo histórico del aire acondicionado, lo que corresponde con la intención de consultar valores de consumo energético ya registrados. El escenario "consumo_basico" es adecuado porque el usuario busca acceder a datos puntuales sin realizar comparaciones analíticas. | C6: 1 | D6: The model correctly identified a single intention from the input, accurately classifying it as 'consumo_basico', which aligns perfectly with the Expected Output. The 'notas' field provides clear and consistent reasoning for this classification, demonstrating strong internal coherence and adherence to all evaluation criteria (A1-A4, B1). | E6: ¿Cuánto consumió el aire acondicionado el fin de semana pasado?
A7: =_xlfn.XLOOKUP(E7,Orden_preguntas!$B:$B,Orden_preguntas!$A:$A) -> 6 | B7: {'@1': {'solicitud': 'Consumo del ventilador el día de ayer', 'escenario': 'consumo_basico'}, '@2': {'solicitud': '', 'escenario': 'entrada_inadmisible'}} | notas: La solicitud se categoriza en el escenario 'consumo_basico' porque solicita valores de consumo energético históricos para un dispositivo específico (el ventilador) y menciona un período de tiempo explícito (el día de ayer). La segunda solicitud no está relacionada con consumo energético y por lo tanto se categoriza en el escenario 'entrada_inadmisible'. | C7: 0.3 | D7: The model fails in the decomposition of the input by generating two requests when only one is present in the 'Input'. Specifically, it incorrectly creates an empty request '@2' and assigns it the 'entrada_inadmisible' scenario, which is an invention of information not deducible from the 'Input'. While the first request '@1' correctly interprets the user's intention and assigns the correct 'consumo_basico' scenario, the overall decomposition and the invention of the second, inadmissible request lead to insufficient semantic quality (A1-A4). | E7: Muéstrame el consumo del ventilador el día de ayer.
A8: =_xlfn.XLOOKUP(E8,Orden_preguntas!$B:$B,Orden_preguntas!$A:$A) -> 7 | B8: {'1': {'solicitud': 'El consumo energético de mi horno el 15 de noviembre', 'escenario': 'consumo_basico'}, '2': {'solicitud': 'Consumo energético del horno en noviembre', 'escenario': 'consumo_basico'}} | notas: Se han categorizado las solicitudes como corresponde al escenario de consumo básico ya que se solicitan valores de consumo energético históricos con fechas explícitas. | C8: 0.3 | D8: The model incorrectly decomposes the input by generating two requests when only one specific request was present. The second request, 'Consumo energético del horno en noviembre,' invents information not deducible from the input, which specifically asked for 'el 15 de noviembre.' This demonstrates a failure in criteria A1 and A2, as the model invents information and does not correctly interpret the input's natural language as a single, precise query, leading to insufficient semantic quality. | E8: ¿Cuál fue el consumo energético de mi horno el 15 de noviembre?
A9: =_xlfn.XLOOKUP(E9,Orden_preguntas!$B:$B,Orden_preguntas!$A:$A) -> 8 | B9: {'@1': {'solicitud': 'Se requiere la cantidad de kWh que consumió mi casa durante la semana pasada', 'escenario': 'consumo_basico'}, '@2': {'solicitud': '', 'escenario': ''}} | notas: El sistema clasificó la solicitud como un escenario básico de consumo porque el usuario solicitó valores históricos de consumo energético, específicamente para una semana pasada. Este escenario se ajusta a las características del 'consumo_basico'. | C9: 0.7 | D9: The model correctly interprets the user's intention to query historical energy consumption for the house last week (A3) and accurately assigns the 'consumo_basico' scenario (B1). The 'notas' field is clear and coherent (A4). However, the decomposition is not entirely correct (A1) because the 'Actual Output' includes an unnecessary and empty request ('@2'), which deviates from the 'Expected Output' that correctly identifies only one request. This minor flaw in decomposition prevents a higher score, despite the correct classification of the primary request. | E9: Dime cuántos kWh consumió mi casa la semana pasada.
A10: =_xlfn.XLOOKUP(E10,Orden_preguntas!$B:$B,Orden_preguntas!$A:$A) -> 9 | B10: {'@1': {'solicitud': '¿Cuánto consumió mi nevera durante el mes de enero?', 'escenario': 'consumo_basico', 'notas': 'La solicitud solicita un valor cuantitativo específico del consumo energético histórico de la nevera, dentro de un intervalo temporal explícito (el mes de enero). Se requiere acceso a datos puntuales para responder.'}} | notas: Se seleccionó el escenario de 'consumo_basico' porque la solicitud solicita una consulta sobre valores de consumo energético históricos específicos, dentro de un intervalo temporal explícito (el mes de enero). | C10: 0.9 | D10: The model correctly decomposes the single input request into one independent request (A1) and does not invent any information (A2). The inferred intention in the 'solicitud' field, although using the exact input phrase instead of rephrasing, accurately aligns with the 'Expected Output's interpretation of querying energy consumption for the fridge in January (A3). The assigned scenario 'consumo_basico' is correct and matches the 'Expected Output' (B1). Furthermore, the 'notas' field provides a clear and coherent explanation for the scenario selection, referencing the specific details of the request (A4). | E10: ¿Cuánto consumió mi nevera durante el mes de enero?
A11: =_xlfn.XLOOKUP(E11,Orden_preguntas!$B:$B,Orden_preguntas!$A:$A) -> 10 | B11: {'@1': {'solicitud': '¿Qué tan feliz estuvo mi casa ayer con el consumo de energía?', 'escenario': 'consumo_basico', 'notas': 'La intención principal es acceder a datos puntuales o históricos sin realizar comparaciones analíticas, análisis de patrones, inferencias ni estimaciones.'}} | notas: La solicitud puede ser categorizada como una consulta de consumo básico porque el usuario pregunta sobre la felicidad de su casa en relación con el consumo energético del día anterior, lo cual se ajusta a la descripción del escenario de consumo_basico. | C11: 0.2 | D11: The model incorrectly classifies the input '¿Qué tan feliz estuvo mi casa ayer con el consumo de energía?' as 'consumo_basico' (B1 failure). The input is a metaphorical, non-technical query, which the Expected Output correctly identifies as 'entrada_inadmisible'. Furthermore, the reasoning provided in the 'notas' field is semantically incoherent (A4 failure), attempting to justify the 'consumo_basico' classification by claiming that asking about the 'happiness' of a house 'se ajusta a la descripción del escenario de consumo_basico' (which is for accessing 'datos puntuales o históricos'). This demonstrates a fundamental misunderstanding of the input's meaning and the scenario's definition. | E11: ¿Qué tan feliz estuvo mi casa ayer con el consumo de energía?
A12: =_xlfn.XLOOKUP(E12,Orden_preguntas!$B:$B,Orden_preguntas!$A:$A) -> 11 | B12: {'@1': {'solicitud': 'Consulta del consumo energético histórico de la nevera y la lavadora para ayer.', 'escenario': 'consumo_basico'}, '@2': {'solicitud': 'Consulta del consumo energético histórico de la nevera y la lavadora para ayer.', 'escenario': 'consumo_basico'}} | notas: El usuario solicita valores de consumo energético históricos específicos para dispositivos (nevera y lavadora) durante un período temporal explícito (ayer), por lo que corresponde a escenarios de entrada admitidos por el sistema relacionados con consultas básicas sobre consumo. | C12: 0.2 | D12: The actual output fails to correctly decompose the input into individual, independent intentions (A1). Both decomposed requests, '@1' and '@2', contain the exact same combined 'solicitud' for 'nevera y lavadora', instead of separating them into distinct requests for each appliance as indicated by the input and expected output. This represents a significant shortcoming in the semantic quality of the decomposition, despite the correct scenario classification ('consumo_basico') and the absence of invented information. | E12: Dime el consumo de mi nevera ayer y el consumo de mi lavadora ayer.
A13: =_xlfn.XLOOKUP(E13,Orden_preguntas!$B:$B,Orden_preguntas!$A:$A) -> 12 | B13: {'@1': {'solicitud': '¿Cuánto consumieron el televisor y el computador el sábado pasado?', 'escenario': 'consumo_basico'}} | notas: La solicitud se corresponde con el escenario de consumo básico porque la intención principal es consultar valores de consumo energético históricos para dispositivos específicos (el televisor y el computador) dentro de un intervalo temporal explícito o claramente inferible. | C13: 0.3 | D13: The model failed to correctly decompose the input into all individual, independent intentions (A1). It treated 'el televisor y el computador' as a single request, whereas the expected output correctly identified two distinct requests for each device. While the scenario classification for the combined request was correct, the fundamental failure in decomposition places the response in the lower score range. | E13: ¿Cuánto consumieron el televisor y el computador el sábado pasado?
... A51: =_xlfn.XLOOKUP(E51,Orden_preguntas!$B:$B,Orden_preguntas!$A:$A) -> 50 | B51: {'@1': {'solicitud': 'Dime el consumo de mi nevera ayer', 'escenario': 'consumo_basico'}, '@2': {'solicitud': 'Compara el consumo de la nevera con la lavadora', 'escenario': 'comparacion_consumos'}, '@3': {'solicitud': 'Dime si con eso ya puedo ahorrar para irme de viaje', 'escenario': 'prediccion_estimacion'}} | notas: Para la primera solicitud, se ha seleccionado el escenario de consumo básico porque el usuario solicita información específica sobre el consumo histórico de su nevera. Para la segunda solicitud, se ha elegido comparar consumos debido a que el usuario pide una comparación directa entre dos dispositivos. La tercera solicitud fue asignada al escenario de predicción y estimación porque el usuario pregunta si puede ahorrar dinero para un viaje, lo que implica necesitar hacer alguna proyección o inferencia sobre sus costos futuros. | C51: 0.6 | D51: El modelo descompone correctamente la entrada en tres solicitudes independientes y su interpretación de las intenciones del usuario es adecuada para las solicitudes '@1' y '@2'. Las 'notas' también son claras y coherentes. Sin embargo, el modelo clasifica incorrectamente la tercera solicitud, 'Dime si con eso ya puedo ahorrar para irme de viaje', como 'prediccion_estimacion'. La clasificación correcta, según el 'Expected Output', debería ser 'entrada_inadmisible', lo que indica que el modelo no reconoce los límites de su dominio para esta petición específica. | E51: Dime el consumo de mi nevera ayer, compárala con la lavadora y dime si con eso ya puedo ahorrar para irme de viaje.

Sheet mistral_7b
A1: ID_PREGUNTA | B1: Respuesta_Modelo | C1: Puntaje_Calidad | D1: Razon_del_Juez | E1: Pregunta
A2: =_xlfn.XLOOKUP(E2,Orden_preguntas!$B:$B,Orden_preguntas!$A:$A) -> 1 | B2: {'@1': {'solicitud': 'Consulta histórica del consumo diario de un dispositivo específico (televisor)', 'escenario': 'consumo_basico'}} | notas: La consulta se relaciona explícitamente con el consumo energético histórico del hogar, más precisamente de un dispositivo específico (televisor) y en un periodo determinado (ayer). El usuario no menciona comparaciones analíticas, análisis de patrones ni inferencias, lo que coincide con el escenario 'consumo_basico'. | C2: 0.9 | D2: The model correctly decomposes the input into a single request and accurately interprets the user's intention to query historical consumption for a specific device (televisor) during a defined period ('ayer en la noche'). The assigned scenario 'consumo_basico' aligns perfectly with the nature of the request, and the 'notas' provide a clear and coherent justification for both the request interpretation and the scenario classification. The 'solicitud' in the actual output uses 'consumo diario' which is a slight generalization compared to 'noche de ayer' in the expected output, but it doesn't invent information or misinterpret the core intent, hence a high score. | E2: ¿Cuánto consumió mi televisor ayer en la noche?
A3: =_xlfn.XLOOKUP(E3,Orden_preguntas!$B:$B,Orden_preguntas!$A:$A) -> 2 | B3: {'@1': {'solicitud': 'El usuario solicita un valor de consumo energético histórico específico para su lavadora el lunes pasado.', 'escenario': 'consumo_basico'}} | notas: La consulta incluye un periodo de tiempo explícito y claramente inferible, y la respuesta esperada es un valor cuantitativo único. | C3: 1 | D3: The model correctly decomposes the input into a single intention (A1) without inventing information (A2). It accurately classifies the request as 'consumo_basico' (B1), matching the Expected Output. The 'notas' field provides a clear and consistent explanation for the identified request and its classification, demonstrating strong internal coherence (A4). The model correctly infers the explicit intention for historical consumption (A3). | E3: Dime el consumo de mi lavadora el lunes pasado.
A4: =_xlfn.XLOOKUP(E4,Orden_preguntas!$B:$B,Orden_preguntas!$A:$A) -> 3 | B4: {'@1': {'solicitud': 'Consultar consumo total del hogar durante marzo de 2024', 'escenario': 'consumo_basico'}} | notas: La solicitud especifica un periodo de tiempo explícito (marzo de 2024) y busca valores cuantitativos, por lo que se categoriza como un escenario de consumo básico. | C4: 1 | D4: The model correctly decomposes the single input request into an individual request (A1) without inventing any information (A2). The inferred intention in the 'solicitud' field, 'Consultar consumo total del hogar durante marzo de 2024', accurately interprets the input '¿Cuál fue el consumo total de la casa durante marzo de 2024?', aligning closely with the expected output's interpretation (A3). The assigned scenario 'consumo_basico' is correct and matches the expected output (B1). Furthermore, the 'notas' field provides a clear and coherent explanation for the classification, stating that the request specifies an explicit time period and seeks quantitative values (A4). | E4: ¿Cuál fue el consumo total de la casa durante marzo de 2024?
A5: =_xlfn.XLOOKUP(E5,Orden_preguntas!$B:$B,Orden_preguntas!$A:$A) -> 4 | B5: {'@1': {'solicitud': 'Solicitud de consulta del consumo energético diario del computador', 'escenario': 'consumo_basico'}} | notas: El usuario ha solicitado información puntual sobre el consumo diario de su computador, lo que corresponde al escenario de entrada 'consumo_basico'. No hay necesidad de realizar comparaciones analíticas ni estimaciones. | C5: 1 | D5: The model correctly decomposed the input into a single request, accurately reflecting the user's intention to query daily computer energy consumption (A1, A2, A3). The 'solicitud' field, 'Solicitud de consulta del consumo energético diario del computador', precisely matches the intent of 'Quiero saber cuánta energía gastó mi computador hoy'. Furthermore, the model correctly classified this request under the 'consumo_basico' scenario, aligning perfectly with the Expected Output (B1). The 'notas' field provides a clear and coherent explanation for this classification (A4). | E5: Quiero saber cuánta energía gastó mi computador hoy.
A6: =_xlfn.XLOOKUP(E6,Orden_preguntas!$B:$B,Orden_preguntas!$A:$A) -> 5 | B6: {'@1': {'solicitud': 'Consulta de consumo energético histórico para un dispositivo específico', 'escenario': 'consumo_basico'}} | notas: La solicitud del usuario busca un valor cuantitativo único referente al consumo del aire acondicionado durante el fin de semana pasado, lo que se encuentra en la categoría 'consumo_basico'. No hay necesidad de realizar comparaciones analíticas ni inferencias. | C6: 1 | D6: El modelo descompone correctamente la intención del usuario '¿Cuánto consumió el aire acondicionado el fin de semana pasado?' en 'Consulta de consumo energético histórico para un dispositivo específico' (A1, A2). La clasificación del escenario como 'consumo_basico' es correcta y coincide con el Expected Output (B1). Además, la explicación en el campo 'notas' es clara y coherente con la solicitud identificada y su clasificación, justificando por qué se categoriza como 'consumo_basico' (A4). No se inventa información ni se omiten intenciones implícitas relevantes (A3). | E6: ¿Cuánto consumió el aire acondicionado el fin de semana pasado?
A7: =_xlfn.XLOOKUP(E7,Orden_preguntas!$B:$B,Orden_preguntas!$A:$A) -> 6 | B7: {'@1': {'solicitud': 'Consultar consumo histórico de un dispositivo (ventilador) para un día específico (el día de ayer)', 'escenario': 'consumo_basico'}} | notas: La consulta es explícita y claramente relacionada con el consumo energético del hogar, solicita datos históricos de un dispositivo específico para un día especificado. El sistema interpreta esta solicitud como una consulta de tipo 'consumo_basico'. | C7: 1 | D7: The model accurately decomposes the input 'Muéstrame el consumo del ventilador el día de ayer' into the correct intention, 'Consultar consumo histórico de un dispositivo (ventilador) para un día específico (el día de ayer)', aligning with A1 and A2. The scenario 'consumo_basico' is correctly assigned (B1), and the 'notas' provide clear, coherent reasoning (A4), demonstrating full compliance with the evaluation criteria. | E7: Muéstrame el consumo del ventilador el día de ayer.
A8: =_xlfn.XLOOKUP(E8,Orden_preguntas!$B:$B,Orden_preguntas!$A:$A) -> 7 | B8: {'@1': {'solicitud': 'Consulta de consumo energético histórico para un dispositivo específico', 'escenario': 'consumo_basico'}} | notas: La consulta es específica sobre el horno y el día concreto del 15 de noviembre, lo que hace claro que se trata de una solicitud para acceder a datos puntuales sin realizar comparaciones ni análisis. | C8: 0.9 | D8: El modelo descompone correctamente la solicitud del usuario en una única intención y no inventa información. La clasificación del escenario como 'consumo_basico' es correcta y coincide con el Expected Output. La nota proporcionada es coherente y justifica adecuadamente la clasificación, mencionando la especificidad del horno y la fecha del 15 de noviembre. La 'solicitud' identificada en el Actual Output es funcionalmente correcta, aunque ligeramente menos específica que la del Expected Output, lo cual no afecta la clasificación ni la comprensión general de la intención. | E8: ¿Cuál fue el consumo energético de mi horno el 15 de noviembre?
A9: =_xlfn.XLOOKUP(E9,Orden_preguntas!$B:$B,Orden_preguntas!$A:$A) -> 8 | B9: {'@1': {'solicitud': 'Consultar el consumo energético histórico de la casa durante la semana pasada', 'escenario': 'consumo_basico'}} | notas: La consulta es explícita en su intención de obtener información de consumo energético, se menciona un período de tiempo claramente inferible (la semana pasada) y el resultado esperado es un valor único. | C9: 0.9 | D9: The model correctly decomposed the single request from the input 'Dime cuántos kWh consumió mi casa la semana pasada' into an independent request without inventing information. The inferred intention 'Consultar el consumo energético histórico de la casa durante la semana pasada' accurately reflects the input and closely aligns with the expected output's interpretation. The assigned scenario 'consumo_basico' is correct and matches the expected output. The 'notas' field provides a clear and coherent explanation of the request, demonstrating strong semantic understanding. | E9: Dime cuántos kWh consumió mi casa la semana pasada.
A10: =_xlfn.XLOOKUP(E10,Orden_preguntas!$B:$B,Orden_preguntas!$A:$A) -> 9 | B10: {'@1': {'solicitud': 'Consultar consumo específico de un dispositivo durante un periodo de tiempo', 'escenario': 'consumo_basico'}} | notas: La consulta solicita los datos históricos de consumo energético de una nevera, específicamente durante el mes de enero. El usuario no pide comparaciones ni análisis, sino simplemente un valor cuantitativo. | C10: 0.9 | D10: The model correctly decomposes the input into a single request (A1) and does not invent information (A2). The inferred intention, 'Consultar consumo específico de un dispositivo durante un periodo de tiempo', accurately captures the essence of '¿Cuánto consumió mi nevera durante el mes de enero?' (A3), with the 'notas' field providing the specific details (nevera, enero) that align with the expected output's specificity. The assigned scenario 'consumo_basico' is correct for a basic consumption query (B1), and the 'notas' are clear and coherent (A4). The slight difference in generality of the 'solicitud' field compared to the expected output is fully compensated by the detailed 'notas', making the overall interpretation robust. | E10: ¿Cuánto consumió mi nevera durante el mes de enero?
A11: =_xlfn.XLOOKUP(E11,Orden_preguntas!$B:$B,Orden_preguntas!$A:$A) -> 10 | B11: {'@1': {'solicitud': 'Consulta del consumo energético total de la casa en un día específico', 'escenario': 'consumo_basico'}} | notas: La consulta incluye una fecha implícita (ayer) y el usuario solicita información cuantitativa acerca del consumo energético total, por lo que se ajusta al escenario de "consumo_basico". | C11: 0.2 | D11: The model fundamentally misinterprets the user's intention. The input '¿Qué tan feliz estuvo mi casa ayer con el consumo de energía?' is an anthropomorphic, non-technical query. The model invents information by inferring a 'Consulta del consumo energético total' (A2) when the input asks about 'happiness'. This leads to an incorrect interpretation (A3) and an incorrect scenario classification of 'consumo_basico' (B1), as the intention does not correspond to a valid technical action in the energy domain, as correctly identified by the Expected Output's 'entrada_inadmisible' scenario. | E11: ¿Qué tan feliz estuvo mi casa ayer con el consumo de energía?
A12: =_xlfn.XLOOKUP(E12,Orden_preguntas!$B:$B,Orden_preguntas!$A:$A) -> 11 | B12: {'@1': {'solicitud': 'Solicitar consumo energético histórico de la nevera del día anterior', 'escenario': 'consumo_basico'}, '@2': {'solicitud': 'Solicitar consumo energético histórico de la lavadora del día anterior', 'escenario': 'consumo_basico'}} | notas: Las solicitudes son explícitas y se pueden categorizar como consultas de datos puntuales históricos sin realizar comparaciones analíticas ni estimaciones, además de tener un periodo de tiempo claramente inferible (el día anterior). | C12: 1 | D12: The model correctly decomposes the input into two independent intentions for the refrigerator and washing machine, aligning perfectly with the Expected Output (A1). It does not invent any information (A2). The implicit intention of 'ayer' (yesterday) is correctly inferred as 'del día anterior' for both requests (A3). Both requests are accurately classified under the 'consumo_basico' scenario, which is consistent with the nature of historical, punctual energy consumption queries (B1). The 'notas' field provides clear and coherent reasoning that supports the identified requests and their classifications (A4). All evaluation criteria are met successfully. | E12: Dime el consumo de mi nevera ayer y el consumo de mi lavadora ayer.
A13: =_xlfn.XLOOKUP(E13,Orden_preguntas!$B:$B,Orden_preguntas!$A:$A) -> 12 | B13: {'1': {'solicitud': 'Consulta histórica de consumo para dos dispositivos específicos en un día concreto', 'escenario': 'consumo_basico'}} | notas: La consulta incluye dos dispositivos específicos (televisor y computador) y un día concreto (el sábado pasado), lo que coincide con el escenario de consumo basico, donde la intención es consultar valores de consumo energético ya registrados para uno o varios dispositivos dentro de un intervalo temporal explícito o claramente inferible. | C13: 0.4 | D13: The model failed to correctly decompose the input into individual, independent requests, as specified in evaluation step A1. The input asks about 'el televisor y el computador', which the Expected Output correctly breaks down into two distinct requests. However, the Actual Output combines these into a single request for 'dos dispositivos específicos', indicating a shortcoming in granular decomposition. While the identified scenario 'consumo_basico' and the general intent were correct for its single interpretation, the fundamental failure to decompose into separate entities aligns with the 0-4 rubric range for failing in request decomposition (A1) and not aligning with the Expected Output's interpretation (A3). | E13: ¿Cuánto consumieron el televisor y el computador el sábado pasado?
... A51: =_xlfn.XLOOKUP(E51,Orden_preguntas!$B:$B,Orden_preguntas!$A:$A) -> 50 | B51: {'@1': {'solicitud': 'Consulta histórica de consumo de la nevera y lavadora para comparación', 'escenario': 'comparacion_consumos'}} | notas: La consulta específica pide comparar dos dispositivos (nevera y lavadora) y menciona explícitamente una intención de hacer análisis comparativos. El contexto implica que se está buscando identificar diferencias en los consumos para determinar cuáles consumen más o menos energía, lo cual es consistente con el escenario 'comparacion_consumos'. | C51: 0.2 | D51: The model fails significantly in decomposing the input, identifying only one request instead of the three distinct requests present in the 'Input'. It incorrectly merges the initial query for the refrigerator's consumption and the comparison with the washing machine into a single request, missing the specific 'consumo_basico' aspect. Crucially, it completely omits the third request, 'dime si con eso ya puedo ahorrar para irme de viaje', which the 'Expected Output' correctly identifies as an 'entrada_inadmisible'. This demonstrates a severe shortcoming in criteria A1 (decomposition) and A3 (interpretation of intentions), leading to insufficient semantic quality. | E51: Dime el consumo de mi nevera ayer, compárala con la lavadora y dime si con eso ya puedo ahorrar para irme de viaje.

Sheet llama33_70b
A1: ID_PREGUNTA | B1: Respuesta_Modelo | C1: Puntaje_Calidad | D1: Razon_del_Juez | E1: Pregunta
A2: =_xlfn.XLOOKUP(E2,Orden_preguntas!$B:$B,Orden_preguntas!$A:$A) -> 1 | B2: {'@1': {'solicitud': 'Consumo de energía del televisor la noche del día anterior', 'escenario': 'consumo_basico'}} | notas: La solicitud se categoriza como 'consumo_basico' porque el usuario solicita un valor de consumo energético específico para un dispositivo (televisor) en un intervalo temporal explícito (ayer en la noche), lo que se ajusta a la descripción del escenario 'consumo_basico' que busca acceder a datos puntuales o históricos sin realizar comparaciones analíticas. | C2: 0.9 | D2: The model correctly decomposed the input into a single request, accurately interpreting the user's intention to query the TV's energy consumption from the previous night (A1, A2, A3). It assigned the correct 'consumo_basico' scenario, which aligns with the request for specific historical consumption data for a device (B1). The 'notas' field provided a clear and coherent explanation for this classification (A4). | E2: ¿Cuánto consumió mi televisor ayer en la noche?
A3: =_xlfn.XLOOKUP(E3,Orden_preguntas!$B:$B,Orden_preguntas!$A:$A) -> 2 | B3: {'@1': {'solicitud': 'Dime el consumo de mi lavadora el lunes pasado', 'escenario': 'consumo_basico'}} | notas: La solicitud se categoriza como 'consumo_basico' porque el usuario solicita un valor de consumo energético histórico para un dispositivo específico (lavadora) dentro de un intervalo temporal explícito (el lunes pasado). | C3: 1 | D3: The model correctly decomposes the input into a single request (A1) without inventing information (A2). The inferred intention in the 'solicitud' field, 'Dime el consumo de mi lavadora el lunes pasado', accurately reflects the input's natural language and aligns with the 'Expected Output's interpretation (A3). The assigned scenario 'consumo_basico' is correct and matches the 'Expected Output' (B1). Furthermore, the 'notas' field provides a clear and coherent explanation for the scenario classification, referencing the specific device (lavadora) and temporal interval (lunes pasado) from the input (A4). | E3: Dime el consumo de mi lavadora el lunes pasado.
A4: =_xlfn.XLOOKUP(E4,Orden_preguntas!$B:$B,Orden_preguntas!$A:$A) -> 3 | B4: {'@1': {'solicitud': 'Consumo total de la casa durante marzo de 2024', 'escenario': 'consumo_basico'}} | notas: La solicitud se categoriza como 'consumo_basico' porque el usuario solicita un valor de consumo energético histórico para un intervalo temporal explícito (marzo de 2024) y se refiere a un dispositivo o zona específica (la casa completa), lo que se ajusta a la descripción del escenario 'consumo_basico'. La respuesta esperada es un valor cuantitativo único que representa el consumo total de la casa durante el mes de marzo de 2024. | C4: 1 | D4: The model correctly decomposes the single request from the input, identifying 'Consumo total de la casa durante marzo de 2024' without inventing any information (A1, A2). Its interpretation of the user's intention aligns perfectly with the Expected Output, despite minor phrasing differences ('la casa' vs 'el hogar') (A3). Furthermore, the model accurately assigns the 'consumo_basico' scenario, which matches the Expected Output and is well-justified in the 'notas' field by referencing the request for historical energy consumption for a specific time and zone (B1). The 'notas' field itself is clear, coherent, and provides excellent reasoning for the classification (A4). | E4: ¿Cuál fue el consumo total de la casa durante marzo de 2024?
A5: =_xlfn.XLOOKUP(E5,Orden_preguntas!$B:$B,Orden_preguntas!$A:$A) -> 4 | B5: {'@1': {'solicitud': 'Quiero saber cuánta energía gastó mi computador hoy', 'escenario': 'consumo_basico'}} | notas: La solicitud se categoriza como 'consumo_basico' porque el usuario solicita un valor de consumo energético específico para un dispositivo (computador) en un intervalo temporal explícito (hoy), lo que se ajusta a la descripción del escenario 'consumo_basico' que busca acceder a datos puntuales o históricos sin realizar comparaciones analíticas. | C5: 1 | D5: The model correctly decomposes the input into a single intention, which aligns with the Expected Output. It does not invent any information. The assigned scenario classification 'consumo_basico' is correct and matches the Expected Output. Furthermore, the 'notas' field provides a clear and consistent explanation for this classification, demonstrating strong internal coherence. All criteria for A1-A4 and B1 are met. | E5: Quiero saber cuánta energía gastó mi computador hoy.
A6: =_xlfn.XLOOKUP(E6,Orden_preguntas!$B:$B,Orden_preguntas!$A:$A) -> 5 | B6: {'@1': {'solicitud': 'Consumo del aire acondicionado el fin de semana pasado', 'escenario': 'consumo_basico'}} | notas: La solicitud se categoriza como 'consumo_basico' porque el usuario solicita un valor de consumo energético histórico para un dispositivo específico (aire acondicionado) dentro de un intervalo temporal explícito (el fin de semana pasado). | C6: 1 | D6: The model correctly decomposes the input into a single, independent request without inventing any information (A1, A2). The inferred intention in the 'solicitud' field, 'Consumo del aire acondicionado el fin de semana pasado', accurately reflects the user's query and aligns perfectly with the 'Expected Output' (A3). Furthermore, the assigned scenario 'consumo_basico' is correct and matches the 'Expected Output' (B1). The 'notas' field provides a clear and coherent explanation for the categorization, demonstrating a strong understanding of the request (A4). | E6: ¿Cuánto consumió el aire acondicionado el fin de semana pasado?
A7: =_xlfn.XLOOKUP(E7,Orden_preguntas!$B:$B,Orden_preguntas!$A:$A) -> 6 | B7: {'@1': {'solicitud': 'Mostrar el consumo del ventilador el día de ayer', 'escenario': 'consumo_basico'}} | notas: La solicitud se categoriza como 'consumo_basico' porque el usuario solicita un valor de consumo energético histórico para un dispositivo específico (el ventilador) dentro de un intervalo temporal explícito (el día de ayer). La intención es acceder a un dato puntual sin realizar comparaciones analíticas, análisis de patrones, inferencias ni estimaciones. | C7: 1 | D7: The model correctly decomposes the single input request into an independent request (A1) without inventing information (A2). The inferred intention in the 'solicitud' field, 'Mostrar el consumo del ventilador el día de ayer', accurately interprets the input's natural language and aligns semantically with the 'Expected Output's 'Consultar el consumo energético del ventilador durante el día de ayer.' (A3). The assigned scenario 'consumo_basico' is correct and matches the 'Expected Output' (B1). Furthermore, the 'notas' field provides a clear, coherent, and accurate justification for the chosen scenario, demonstrating strong internal consistency (A4). | E7: Muéstrame el consumo del ventilador el día de ayer.
A8: =_xlfn.XLOOKUP(E8,Orden_preguntas!$B:$B,Orden_preguntas!$A:$A) -> 7 | B8: {'@1': {'solicitud': 'Consumo energético del horno el 15 de noviembre', 'escenario': 'consumo_basico'}} | notas: La solicitud se categoriza como 'consumo_basico' porque el usuario solicita un valor de consumo energético histórico para un dispositivo específico (horno) en una fecha determinada (15 de noviembre), lo que se ajusta a la descripción del escenario 'consumo_basico' que busca acceder a datos puntuales o históricos sin realizar comparaciones analíticas. | C8: 1 | D8: El modelo descompone correctamente la intención del usuario en una única solicitud ('Consumo energético del horno el 15 de noviembre') sin inventar información, lo cual satisface A1 y A2. La clasificación del escenario como 'consumo_basico' es correcta y coincide con el Expected Output, cumpliendo B1 y A3. Además, la explicación en el campo 'notas' es clara, detallada y coherente con la solicitud y su clasificación, justificando por qué se ajusta a 'consumo_basico' al mencionar la solicitud de un valor histórico para un dispositivo y fecha específicos sin comparaciones, lo que demuestra una excelente coherencia interna (A4). | E8: ¿Cuál fue el consumo energético de mi horno el 15 de noviembre?
A9: =_xlfn.XLOOKUP(E9,Orden_preguntas!$B:$B,Orden_preguntas!$A:$A) -> 8 | B9: {'@1': {'solicitud': 'Dime cuántos kWh consumió mi casa la semana pasada', 'escenario': 'consumo_basico'}} | notas: La solicitud se categoriza como 'consumo_basico' porque el usuario solicita un valor de consumo energético histórico para un intervalo temporal explícito (la semana pasada), lo que se ajusta a la descripción del escenario 'consumo_basico'. La respuesta esperada es un valor cuantitativo único, que es el consumo total de kWh de la casa durante ese período. | C9: 1 | D9: The model correctly decomposes the input into a single intention (A1) without inventing information (A2). The assigned scenario classification 'consumo_basico' is correct and aligns with the Expected Output (B1). The 'notas' field provides clear and consistent reasoning for the classification, demonstrating strong internal coherence (A4). All criteria from A1 to A4 and B1 are met, indicating a complete and accurate response for the input 'Dime cuántos kWh consumió mi casa la semana pasada'. | E9: Dime cuántos kWh consumió mi casa la semana pasada.
A10: =_xlfn.XLOOKUP(E10,Orden_preguntas!$B:$B,Orden_preguntas!$A:$A) -> 9 | B10: {'@1': {'solicitud': 'Consumo de la nevera en enero', 'escenario': 'consumo_basico'}} | notas: La solicitud se categoriza como 'consumo_basico' porque el usuario solicita un valor de consumo energético histórico para un dispositivo específico (la nevera) dentro de un intervalo temporal explícito (el mes de enero). La respuesta esperada es un valor cuantitativo único. | C10: 0.9 | D10: The model correctly decomposed the single input request into an independent request, accurately interpreting the user's intention to query the fridge's consumption in January. It assigned the correct 'consumo_basico' scenario, which aligns with the expected output. The 'notas' field provided a clear and coherent justification for this classification, demonstrating strong adherence to criteria A1-A4 and B1. | E10: ¿Cuánto consumió mi nevera durante el mes de enero?
A11: =_xlfn.XLOOKUP(E11,Orden_preguntas!$B:$B,Orden_preguntas!$A:$A) -> 10 | B11: {'@1': {'solicitud': '¿Cuánta energía consumió mi casa ayer?', 'escenario': 'consumo_basico'}} | notas: La solicitud del usuario se categoriza bajo el escenario 'consumo_basico' porque busca un valor de consumo energético histórico para un dispositivo o zona del hogar (en este caso, la casa completa) dentro de un intervalo temporal explícito (ayer). La intención es acceder a un dato puntual sin realizar comparaciones analíticas, análisis de patrones, inferencias ni estimaciones. La pregunta sobre la "feliz" es interpretada como una metáfora para referirse al consumo de energía, lo que sugiere que el usuario está interesado en saber si el consumo fue alto o bajo, pero el sistema lo interpreta como una solicitud de datos de consumo. | C11: 0.2 | D11: The model fails significantly in decomposing the input (A1) and invents information not present (A2). The input asks about the 'happiness' of the house regarding energy consumption, an emotional state. The actual output reinterprets this as '¿Cuánta energía consumió mi casa ayer?', changing the nature of the request from an emotional assessment to a quantitative measurement. This is a fundamental misinterpretation, not a correct decomposition, and introduces information (a request for a quantity) not explicitly stated. The expected output correctly identifies the original intent as 'entrada_inadmisible', highlighting the model's failure to correctly infer the user's implicit intentions (A3) and classify the scenario (B1) based on the actual input. | E11: ¿Qué tan feliz estuvo mi casa ayer con el consumo de energía?
A12: =_xlfn.XLOOKUP(E12,Orden_preguntas!$B:$B,Orden_preguntas!$A:$A) -> 11 | B12: {'@1': {'solicitud': 'Dime el consumo de mi nevera ayer', 'escenario': 'consumo_basico'}, '@2': {'solicitud': 'Dime el consumo de mi lavadora ayer', 'escenario': 'consumo_basico'}} | notas: El sistema ha identificado dos solicitudes claras y directas para obtener el consumo energético de dos dispositivos específicos (nevera y lavadora) en un intervalo temporal explícito (ayer). Ambas solicitudes se ajustan al escenario de "consumo_basico" porque buscan valores de consumo energético históricos para dispositivos específicos dentro de un periodo de tiempo definido, sin realizar comparaciones ni análisis de patrones. | C12: 1 | D12: The model correctly decomposes the input into two independent requests, 'Dime el consumo de mi nevera ayer' and 'Dime el consumo de mi lavadora ayer', without inventing any information (A1, A2). The inferred intentions align perfectly with the Expected Output's interpretation (A3). Both requests are accurately classified under the 'consumo_basico' scenario, matching the Expected Output (B1). Furthermore, the 'notas' field provides a clear and coherent explanation for the classification, demonstrating strong internal consistency (A4). | E12: Dime el consumo de mi nevera ayer y el consumo de mi lavadora ayer.
A13: =_xlfn.XLOOKUP(E13,Orden_preguntas!$B:$B,Orden_preguntas!$A:$A) -> 12 | B13: {'@1': {'solicitud': 'Consumo del televisor el sábado pasado', 'escenario': 'consumo_basico'}, '@2': {'solicitud': 'Consumo del computador el sábado pasado', 'escenario': 'consumo_basico'}} | notas: La solicitud del usuario se refiere a dos dispositivos específicos (televisor y computador) y un período de tiempo explícito (el sábado pasado), lo que indica que la intención principal es consultar valores de consumo energético históricos. Esto se ajusta al escenario de "consumo_basico" ya que se busca acceder a datos puntuales sin realizar comparaciones analíticas, análisis de patrones, inferencias ni estimaciones. | C13: 0.9 | D13: The model correctly decomposes the input '¿Cuánto consumieron el televisor y el computador el sábado pasado?' into two independent requests for the television and the computer (A1). It does not invent any information (A2). The inferred intentions in the 'solicitud' fields ('Consumo del televisor el sábado pasado', 'Consumo del computador el sábado pasado') accurately reflect the user's query and align well with the 'Expected Output' (A3). Both requests are correctly classified under the 'consumo_basico' scenario, matching the 'Expected Output' (B1). The 'notas' field provides a clear and coherent explanation for the decomposition and scenario assignment, detailing the specific devices and time period (A4). | E13: ¿Cuánto consumieron el televisor y el computador el sábado pasado?
... A51: =_xlfn.XLOOKUP(E51,Orden_preguntas!$B:$B,Orden_preguntas!$A:$A) -> 50 | B51: {'@1': {'solicitud': 'Dime el consumo de mi nevera ayer', 'escenario': 'consumo_basico'}, '@2': {'solicitud': 'compárala con la lavadora', 'escenario': 'comparacion_consumos'}, '@3': {'solicitud': 'dime si con eso ya puedo ahorrar para irme de viaje', 'escenario': 'prediccion_estimacion'}} | notas: Se identificaron tres solicitudes en la entrada del usuario. La primera solicitud busca el consumo de la nevera ayer, lo que se ajusta al escenario de 'consumo_basico' porque solicita un valor de consumo energético histórico para un dispositivo específico dentro de un intervalo temporal explícito. La segunda solicitud compara el consumo de la nevera con el de la lavadora, lo que encaja en el escenario de 'comparacion_consumos' porque implica comparar consumos entre dos dispositivos diferentes. La tercera solicitud, sin embargo, se refiere a si con la información proporcionada se puede ahorrar para un viaje, lo que se ajusta al escenario de 'prediccion_estimacion' porque implica una proyección o estimación futura basada en datos actuales. | C51: 0.6 | D51: The model correctly decomposes the input into three distinct intentions and does not invent information. The first two intentions, 'Dime el consumo de mi nevera ayer' and 'compárala con la lavadora', are correctly classified as 'consumo_basico' and 'comparacion_consumos' respectively, aligning with the Expected Output. The internal reasoning provided in the 'notas' field is consistent with these classifications. However, the third intention, 'dime si con eso ya puedo ahorrar para irme de viaje', is incorrectly classified as 'prediccion_estimacion'. The Expected Output clearly indicates this as 'entrada_inadmisible', suggesting it is outside the system's domain. This single incorrect scenario classification prevents a higher score, placing it in the 5-7 range according to the rubric. | E51: Dime el consumo de mi nevera ayer, compárala con la lavadora y dime si con eso ya puedo ahorrar para irme de viaje.

Sheet qwen3_coder_35b_480b
A1: ID_PREGUNTA | B1: Respuesta_Modelo | C1: Puntaje_Calidad | D1: Razon_del_Juez | E1: Pregunta
A2: =_xlfn.XLOOKUP(E2,Orden_preguntas!$B:$B,Orden_preguntas!$A:$A) -> 1 | B2: {'@1': {'solicitud': 'Consultar el consumo energético registrado por el televisor durante la noche del día anterior (ayer).', 'escenario': 'consumo_basico'}} | notas: La solicitud busca obtener un valor específico de consumo energético ya registrado para un dispositivo (televisor) en un periodo de tiempo claramente definido (ayer en la noche). No se realiza ninguna comparación, ni se infiere o estima el consumo, por lo tanto corresponde al escenario 'consumo_basico'. | C2: 1 | D2: The model correctly decomposes the single input request into an independent request (A1). It accurately interprets the user's intention to 'Consultar el consumo energético registrado por el televisor durante la noche del día anterior (ayer)' without inventing information (A2), aligning closely with the 'Consultar el consumo energético del televisor durante la noche de ayer' from the Expected Output (A3). The assigned scenario 'consumo_basico' is correct for a direct query of historical consumption for a specific device and time (B1). Furthermore, the 'notas' field provides a clear and coherent justification for this classification, referencing the specific details of the request (A4). | E2: ¿Cuánto consumió mi televisor ayer en la noche?
A3: =_xlfn.XLOOKUP(E3,Orden_preguntas!$B:$B,Orden_preguntas!$A:$A) -> 2 | B3: {'@1': {'solicitud': 'Consultar el consumo energético registrado para la lavadora durante el día completo del lunes pasado (2026-01-05).', 'escenario': 'consumo_basico'}} | notas: La solicitud busca obtener un valor de consumo energético específico (de la lavadora) en un periodo de tiempo claramente definido (el lunes pasado), lo cual encaja directamente con el escenario "consumo_basico", ya que se trata de una consulta puntual sobre un dato registrado. | C3: 0.9 | D3: The model correctly decomposes the single request from the input 'Dime el consumo de mi lavadora el lunes pasado' into one independent request (A1). It accurately infers the intention to 'Consultar el consumo energético' for the 'lavadora' on 'el lunes pasado', aligning with the expected output's interpretation (A3). While the actual output adds a specific date (2026-01-05) and 'durante el día completo', this is a reasonable and more precise interpretation rather than an invention of information (A2). The assigned scenario 'consumo_basico' is correct and matches the expected output (B1). The 'notas' field clearly explains the reasoning for the scenario, demonstrating coherence (A4). The slight verbosity in the 'solicitud' compared to the expected output is a minor difference that does not detract from the overall correctness and precision. | E3: Dime el consumo de mi lavadora el lunes pasado.
A4: =_xlfn.XLOOKUP(E4,Orden_preguntas!$B:$B,Orden_preguntas!$A:$A) -> 3 | B4: {'@1': {'solicitud': 'Obtener el valor total del consumo energético registrado en todo el hogar durante el mes de marzo de 2024.', 'escenario': 'consumo_basico'}} | notas: La solicitud busca un valor cuantitativo específico del consumo energético total del hogar durante un periodo explícito (marzo de 2024), lo cual encaja con el escenario "consumo_basico", ya que se trata de consultar un dato histórico registrado sin realizar análisis comparativos, detección de anomalías ni predicciones. | C4: 1 | D4: The model correctly decomposes the input into a single, independent intention without inventing information (A1, A2). The assigned scenario classification 'consumo_basico' is correct and aligns with the expected output (B1). The model accurately infers the explicit intention, and no implicit intentions were present to infer (A3). The reasoning provided in the 'notas' field is clear, consistent, and fully supports the identified request and its classification, demonstrating strong internal coherence (A4). | E4: ¿Cuál fue el consumo total de la casa durante marzo de 2024?
A5: =_xlfn.XLOOKUP(E5,Orden_preguntas!$B:$B,Orden_preguntas!$A:$A) -> 4 | B5: {'@1': {'solicitud': 'Consultar el consumo energético registrado para el computador durante el día de hoy.', 'escenario': 'consumo_basico'}} | notas: La solicitud se enfoca en obtener un valor específico de consumo energético para un dispositivo particular (computador) en un periodo de tiempo claramente definido (hoy). Esto corresponde al escenario "consumo_basico", ya que no implica comparaciones, análisis de tendencias, predicciones ni está fuera del dominio del sistema. | C5: 1 | D5: The model correctly decomposes the input 'Quiero saber cuánta energía gastó mi computador hoy' into a single, independent intention. It accurately identifies the request to consult energy consumption for a specific device on a specific day without inventing information. The assigned scenario classification 'consumo_basico' is correct and aligns with the Expected Output. The 'notas' field provides a clear and coherent explanation for this classification, demonstrating strong internal consistency. | E5: Quiero saber cuánta energía gastó mi computador hoy.
A6: =_xlfn.XLOOKUP(E6,Orden_preguntas!$B:$B,Orden_preguntas!$A:$A) -> 5 | B6: {'@1': {'solicitud': '¿Cuánto consumió el aire acondicionado el fin de semana pasado?', 'escenario': 'consumo_basico'}} | notas: La solicitud busca un valor cuantitativo específico del consumo energético de un dispositivo (aire acondicionado) en un periodo de tiempo claramente inferible (fin de semana pasado). No se plantea una comparación, análisis de tendencias ni predicción, sino la consulta directa de un dato histórico, lo cual encaja en el escenario "consumo_basico". | C6: 0.9 | D6: The model correctly decomposes the input into a single intention, which aligns with the Expected Output. It accurately classifies the scenario as 'consumo_basico', matching the Expected Output's classification. The 'notas' field provides a clear and coherent explanation for this classification, demonstrating strong internal consistency. The only minor difference is that the 'solicitud' field in the Actual Output uses the exact input query, while the Expected Output rephrases it slightly, but this does not detract from the correctness of the decomposition or classification. | E6: ¿Cuánto consumió el aire acondicionado el fin de semana pasado?
A7: =_xlfn.XLOOKUP(E7,Orden_preguntas!$B:$B,Orden_preguntas!$A:$A) -> 6 | B7: {'@1': {'solicitud': 'Mostrar el consumo energético del ventilador durante el día de ayer (10 de enero de 2026).', 'escenario': 'consumo_basico'}} | notas: La solicitud busca un valor de consumo energético ya registrado para un dispositivo específico (ventilador) en un periodo de tiempo explícito (el día de ayer), lo cual encaja con el escenario "consumo_basico". | C7: 0.3 | D7: El modelo inventa información no proporcionada en el Input al añadir '(10 de enero de 2026)' a la solicitud, lo cual es una clara violación del criterio A2. Aunque la clasificación del escenario 'consumo_basico' es correcta y la coherencia interna de las notas es adecuada para la solicitud generada, la invención de datos es un fallo crítico que sitúa la respuesta en el rango de 0-4 de la rúbrica. | E7: Muéstrame el consumo del ventilador el día de ayer.
A8: =_xlfn.XLOOKUP(E8,Orden_preguntas!$B:$B,Orden_preguntas!$A:$A) -> 7 | B8: {'@1': {'solicitud': 'Consulta del consumo energético del horno el 15 de noviembre de 2025.', 'escenario': 'consumo_basico'}} | notas: La solicitud busca un valor específico de consumo energético registrado para un dispositivo (el horno) en una fecha concreta (el 15 de noviembre). No implica análisis, comparaciones ni predicciones, por lo que se ajusta al escenario "consumo_basico". | C8: 0.3 | D8: The model correctly identified the single intention and classified it into the 'consumo_basico' scenario, with coherent reasoning in the 'notas'. However, it invented information by adding 'de 2025' to the date '15 de noviembre' in the `solicitud` field, which was not present in the original input. This invention of information (A2) is a significant shortcoming, placing the response in the lowest score range despite other correct aspects. | E8: ¿Cuál fue el consumo energético de mi horno el 15 de noviembre?
A9: =_xlfn.XLOOKUP(E9,Orden_preguntas!$B:$B,Orden_preguntas!$A:$A) -> 8 | B9: {'@1': {'solicitud': 'Consultar el consumo total de energía eléctrica en kWh del hogar completo durante la semana pasada (del 29 de diciembre de 2025 al 4 de enero de 2026)', 'escenario': 'consumo_basico'}} | notas: La solicitud busca un valor cuantitativo específico (kWh consumidos) correspondiente a un periodo de tiempo claramente definido (la semana pasada), sin realizar comparaciones ni análisis adicionales. Por lo tanto, encaja en el escenario 'consumo_basico'. | C9: 0.3 | D9: The model correctly decomposes the request and assigns the correct scenario 'consumo_basico' with a coherent explanation. However, it invents specific dates ('del 29 de diciembre de 2025 al 4 de enero de 2026') for 'la semana pasada' which are not deducible from the input or provided context, and are not present in the expected output. This constitutes inventing information (A2), making the semantic quality insufficient. | E9: Dime cuántos kWh consumió mi casa la semana pasada.
A10: =_xlfn.XLOOKUP(E10,Orden_preguntas!$B:$B,Orden_preguntas!$A:$A) -> 9 | B10: {'@1': {'solicitud': '¿Cuánto consumió mi nevera durante el mes de enero?', 'escenario': 'consumo_basico'}} | notas: La solicitud busca un valor cuantitativo específico de consumo energético (cuánto consumió) referido a un dispositivo particular (la nevera) en un periodo explícito (el mes de enero). Esto encaja directamente con el escenario "consumo_basico", ya que no implica comparaciones, análisis de tendencias, ni proyecciones; simplemente se trata de obtener un dato histórico de consumo. | C10: 1 | D10: The model correctly decomposes the input into a single request, accurately reflecting the user's intention without inventing any information (A1, A2). The inferred intention in the 'solicitud' field aligns perfectly with the 'Expected Output' (A3). Furthermore, the model correctly assigns the 'consumo_basico' scenario, which is consistent with the 'Expected Output' and the nature of the query for a specific historical consumption data point (B1). The 'notas' field provides a clear and coherent explanation for this classification, demonstrating a strong understanding of the request (A4). | E10: ¿Cuánto consumió mi nevera durante el mes de enero?
A11: =_xlfn.XLOOKUP(E11,Orden_preguntas!$B:$B,Orden_preguntas!$A:$A) -> 10 | B11: {'@1': {'solicitud': 'Determinar la satisfacción o felicidad asociada al consumo energético del hogar durante el día de ayer.', 'escenario': 'entrada_inadmisible'}} | notas: La solicitud hace una pregunta abstracta y antropomórfica ("qué tan feliz estuvo mi casa") en relación con el consumo energético, lo cual no se corresponde con ninguno de los escenarios técnicos definidos. No se busca un valor cuantitativo, ni comparación, ni detección de anomalías, ni predicción, sino una interpretación emocional o subjetiva que está fuera del dominio del sistema. | C11: 1 | D11: The model correctly decomposes the input into a single intention, accurately rephrasing '¿Qué tan feliz estuvo mi casa ayer con el consumo de energía?' as 'Determinar la satisfacción o felicidad asociada al consumo energético del hogar durante el día de ayer.' It correctly classifies this intention as 'entrada_inadmisible,' aligning with the Expected Output. The 'notas' field provides a clear and coherent explanation for this classification, referencing the abstract and anthropomorphic nature of the request and its mismatch with technical scenarios, demonstrating strong internal coherence. | E11: ¿Qué tan feliz estuvo mi casa ayer con el consumo de energía?
A12: =_xlfn.XLOOKUP(E12,Orden_preguntas!$B:$B,Orden_preguntas!$A:$A) -> 11 | B12: {'@1': {'solicitud': 'Consultar el consumo energético registrado para la nevera durante el día de ayer.', 'escenario': 'consumo_basico'}, '@2': {'solicitud': 'Consultar el consumo energético registrado para la lavadora durante el día de ayer.', 'escenario': 'consumo_basico'}} | notas: Ambas solicitudes buscan obtener valores puntuales de consumo ya registrados para un dispositivo específico en un periodo de tiempo explícito (ayer). No implican comparaciones, análisis de tendencias ni predicciones, por lo que encajan claramente en el escenario "consumo_basico". | C12: 1 | D12: El modelo descompone correctamente la solicitud del usuario en dos peticiones independientes para la nevera y la lavadora, sin inventar información (A1, A2). La interpretación de las intenciones en las solicitudes del 'Actual Output' es precisa y se alinea con el 'Expected Output' (A3). Ambas solicitudes son clasificadas correctamente en el escenario 'consumo_basico', lo cual es coherente con la naturaleza de las consultas de consumo histórico puntual (B1). Además, el campo 'notas' del 'Actual Output' es claro, coherente y justifica adecuadamente la asignación del escenario (A4). | E12: Dime el consumo de mi nevera ayer y el consumo de mi lavadora ayer.
A13: =_xlfn.XLOOKUP(E13,Orden_preguntas!$B:$B,Orden_preguntas!$A:$A) -> 12 | B13: {'@1': {'solicitud': 'Consultar el consumo energético registrado del televisor el sábado pasado.', 'escenario': 'consumo_basico'}, '@2': {'solicitud': 'Consultar el consumo energético registrado del computador el sábado pasado.', 'escenario': 'consumo_basico'}} | notas: La solicitud del usuario se centra en obtener valores específicos de consumo energético de dos dispositivos (televisor y computador) para un periodo explícito (el sábado pasado). Esto encaja directamente en el escenario "consumo_basico", ya que se está pidiendo un dato cuantitativo puntual de consumo registrado, sin realizar comparaciones, análisis de tendencias ni proyecciones. | C13: 1 | D13: The model correctly decomposes the input '¿Cuánto consumieron el televisor y el computador el sábado pasado?' into two independent requests, one for the television and one for the computer (A1). It does not invent any information, and the inferred intentions align perfectly with the expected output, even with the slight addition of 'registrado' which is an adequate inference of an implicit detail for past consumption data (A2, A3). Both requests are correctly classified under the 'consumo_basico' scenario, aligning with the expected output (B1). The 'notas' field provides a clear and coherent explanation for the decomposition and scenario assignment (A4). | E13: ¿Cuánto consumieron el televisor y el computador el sábado pasado?
... A16: =_xlfn.XLOOKUP(E16,Orden_preguntas!$B:$B,Orden_preguntas!$A:$A) -> 15 | B16: {'@1': {'solicitud': 'Dime el consumo del ventilador esta semana.', 'escenario': 'consumo_basico'}, '@2': {'solicitud': 'Dime el consumo de la lavadora la semana pasada.', 'escenario': 'consumo_basico'}} | notas: Ambas solicitudes buscan consultar valores específicos de consumo energético ya registrado, vinculados a un dispositivo y un periodo de tiempo claramente identificable (esta semana y la semana pasada respectivamente). No implican comparaciones, análisis de tendencias ni proyecciones. Por ello, ambas encajan en el escenario "consumo_basico". | C16: 1 | D16: The model correctly decomposes the input into two independent intentions (A1) without inventing information (A2). It accurately identifies the direct requests for consumption of the 'ventilador esta semana' and 'lavadora la semana pasada'. The scenario classification for both as 'consumo_basico' is correct (B1), aligning with the Expected Output. Furthermore, the 'notas' field provides clear and consistent reasoning for this classification, demonstrating strong internal coherence (A4). The model successfully infers implicit intentions by capturing the core request for consumption data (A3). | E16: Dime el consumo del ventilador esta semana y el de la lavadora la semana pasada.
A17: =_xlfn.XLOOKUP(E17,Orden_preguntas!$B:$B,Orden_preguntas!$A:$A) -> 16 | B17: {'@1': {'solicitud': 'Consultar el consumo energético registrado ayer para el PC, el monitor y el router.', 'escenario': 'consumo_basico'}} | notas: La solicitud del usuario busca obtener valores históricos de consumo energético para dispositivos específicos (PC, monitor, router) dentro de un periodo de tiempo claramente definido (ayer). Esto encaja con el escenario "consumo_basico" porque se centra en acceder a datos puntuales ya registrados sin realizar comparaciones, análisis o inferencias. | C17: 0.8 | D17: The model correctly identified the core request for energy consumption for the specified devices yesterday and classified it correctly as 'consumo_basico' (B1). It did not invent information (A2) and its internal reasoning was coherent (A4). However, it failed to decompose the input into individual, independent intentions for each device (PC, monitor, router) as demonstrated by the Expected Output, instead combining them into a single intention. This constitutes a failure in criterion A1 regarding decomposition granularity, which impacts the overall semantic quality. | E17: ¿Cuánta energía gastaron mi PC, mi monitor y mi router ayer? | F17: El sistema está capacitado para recibir consultas de múltiples dispositivos en el mismo periodo de tiempo. nueva nota: 0.8
A18: =_xlfn.XLOOKUP(E18,Orden_preguntas!$B:$B,Orden_preguntas!$A:$A) -> 17 | B18: {'@1': {'solicitud': 'Mostrar el consumo del horno en enero', 'escenario': 'consumo_basico'}, '@2': {'solicitud': 'Mostrar el consumo del horno en febrero', 'escenario': 'consumo_basico'}} | notas: Ambas solicitudes buscan consultar valores de consumo energético ya registrados para un dispositivo específico (el horno) en intervalos temporales explícitos (enero y febrero). No hay intención de comparar, analizar tendencias, o predecir; se trata de solicitudes de datos históricos puntuales. Por lo tanto, se categorizan como 'consumo_basico'. | C18: 0.9 | D18: The model correctly decomposes the input into two independent intentions (A1) and does not invent information (A2). It also correctly classifies both requests as 'consumo_basico' (B1), aligning with the Expected Output. Furthermore, the reasoning in the 'notas' field is internally coherent with the identified requests and their classifications within the Actual Output (A4). However, the model fails to adequately infer an implicit intention (A3). The Actual Output explicitly states 'No hay intención de comparar', which directly contradicts the Expected Output's note of 'comparación implícita entre periodos' for the input 'Muéstrame el consumo del horno en enero y en febrero'. This failure to infer the implicit comparison means that the condition 'A1–A4 correctos' is not met, placing the score in the 0-4 range due to insufficient semantic quality (A3). | E18: Muéstrame el consumo del horno en enero y en febrero. | F18: Aunque se puede inferir comparación, es válido el no hacerlo. nueva nota: 0.9
A19: =_xlfn.XLOOKUP(E19,Orden_preguntas!$B:$B,Orden_preguntas!$A:$A) -> 18 | B19: {'@1': {'solicitud': '¿Cuánto consumió mi casa en junio de 2026?', 'escenario': 'consumo_basico'}, '@2': {'solicitud': '¿Cuánto consumió mi casa en julio de 2026?', 'escenario': 'consumo_basico'}, '@3': {'solicitud': '¿Cuánto consumió mi casa en agosto de 2026?', 'escenario': 'consumo_basico'}} | notas: Las tres solicitudes buscan consultar valores específicos de consumo energético para períodos concretos (meses de junio, julio y agosto del año en curso, 2026). No implican comparaciones, análisis de tendencias ni proyecciones, sino simplemente la obtención de datos ya registrados, por lo que se clasifican adecuadamente bajo el escenario 'consumo_basico'. | C19: 0.3 | D19: The model correctly decomposes the input into three independent requests and accurately assigns the 'consumo_basico' scenario to each, aligning with the Expected Output's classification. However, it invents the year '2026' for each request ('¿Cuánto consumió mi casa en junio de 2026?'), which is not deducible from the original input '¿Cuánto consumió mi casa en junio, julio y agosto?' and contradicts the Expected Output's more general phrasing. This invention of information violates criterion A2. | E19: ¿Cuánto consumió mi casa en junio, julio y agosto?
A20: =_xlfn.XLOOKUP(E20,Orden_preguntas!$B:$B,Orden_preguntas!$A:$A) -> 19 | B20: {'@1': {'solicitud': 'Quiero saber el consumo de mi nevera el domingo.', 'escenario': 'consumo_basico'}, '@2': {'solicitud': 'Quiero saber el consumo de mi lavadora el domingo.', 'escenario': 'consumo_basico'}, '@3': {'solicitud': 'Quiero saber el consumo de mi secadora el domingo.', 'escenario': 'consumo_basico'}} | notas: Las tres solicitudes buscan consultar valores específicos de consumo energético para dispositivos concretos (nevera, lavadora y secadora) en un día determinado (domingo). Se ajustan al escenario 'consumo_basico' ya que la intención es acceder a datos puntuales de consumo ya registrados dentro de un intervalo temporal explícito. | C20: 1 | D20: The model accurately decomposes the input 'Quiero saber el consumo de mi nevera, mi lavadora y mi secadora el domingo' into three distinct, independent intentions, one for each appliance (A1). It does not invent any information (A2). All three intentions are correctly classified under the 'consumo_basico' scenario (B1), aligning with the Expected Output. The 'notas' field provides a clear and coherent explanation for this classification, demonstrating strong internal consistency between the identified requests and their assigned scenarios (A4). | E20: Quiero saber el consumo de mi nevera, mi lavadora y mi secadora el domingo.
A21: =_xlfn.XLOOKUP(E21,Orden_preguntas!$B:$B,Orden_preguntas!$A:$A) -> 20 | B21: {'@1': {'solicitud': 'Dime el consumo de mi televisor ayer', 'escenario': 'consumo_basico'}, '@2': {'solicitud': 'Dime si el consumo de mi televisor ayer fue moralmente correcto', 'escenario': 'entrada_inadmisible'}} | notas: La primera solicitud busca un valor cuantitativo específico de consumo energético para un dispositivo y un periodo de tiempo concreto (ayer), lo cual encaja en el escenario 'consumo_basico'. La segunda solicitud introduce un juicio moral subjetivo que no puede ser determinado por el sistema de análisis de consumo energético del hogar, por lo tanto corresponde al escenario 'entrada_inadmisible'. | C21: 1 | D21: El modelo descompone correctamente el 'Input' en dos intenciones distintas, 'Dime el consumo de mi televisor ayer' y 'Dime si el consumo de mi televisor ayer fue moralmente correcto', sin inventar información. Clasifica correctamente la primera solicitud como 'consumo_basico' y la segunda como 'entrada_inadmisible', lo cual coincide con el 'Expected Output'. Además, las 'notas' proporcionan un razonamiento claro y coherente que justifica cada clasificación, demostrando una excelente comprensión y aplicación de los criterios A1-A4 y B1. | E21: Dime el consumo de mi televisor ayer y dime también si eso fue moralmente correcto.
A22: =_xlfn.XLOOKUP(E22,Orden_preguntas!$B:$B,Orden_preguntas!$A:$A) -> 21 | B22: {'@1': {'solicitud': '¿Cuánto consumió mi nevera ayer?', 'escenario': 'consumo_basico'}, '@2': {'solicitud': '¿Cuál consumió más, la nevera o el horno?', 'escenario': 'comparacion_consumos'}} | notas: La primera solicitud pregunta por el consumo energético histórico de un dispositivo específico (la nevera) durante un periodo de tiempo claramente definido (ayer), lo cual encaja con el escenario 'consumo_basico'. La segunda solicitud busca comparar el consumo entre dos dispositivos diferentes (nevera vs horno) para determinar cuál tiene un mayor consumo, lo que corresponde al escenario 'comparacion_consumos'. | C22: 0.9 | D22: The model correctly decomposes the input into two independent intentions (A1) and does not invent information (A2). Both intentions are accurately classified as 'consumo_basico' and 'comparacion_consumos' respectively, matching the Expected Output (B1). The reasoning provided in the 'notas' field is clear, consistent, and correctly justifies the assigned scenarios (A4). The only minor shortcoming is that the second intention's text ('¿Cuál consumió más, la nevera o el horno?') does not explicitly infer the temporal context 'durante el día de ayer' from the first part of the input, unlike the Expected Output (A3). However, this does not lead to an incorrect classification or a lack of understanding of the core comparison intent, maintaining a high level of semantic quality. | E22: ¿Cuánto consumió mi nevera ayer y cuál consumió más, la nevera o el horno?
A23: =_xlfn.XLOOKUP(E23,Orden_preguntas!$B:$B,Orden_preguntas!$A:$A) -> 22 | B23: {'@1': {'solicitud': 'Dime el consumo del aire acondicionado esta semana.', 'escenario': 'consumo_basico'}, '@2': {'solicitud': 'Dime el consumo del aire acondicionado la semana pasada.', 'escenario': 'consumo_basico'}, '@3': {'solicitud': 'Compara el consumo del aire acondicionado entre esta semana y la semana pasada.', 'escenario': 'comparacion_consumos'}} | notas: La solicitud original combina dos consultas de valores de consumo (esta semana y la semana pasada) con una comparación entre ambos periodos. Se segmenta en tres solicitudes: las dos primeras son consultas básicas de consumo energético en intervalos temporales definidos (sin comparaciones), por lo que se categorizan como 'consumo_basico'. La tercera solicitud toma esos valores y los compara explícitamente, encajando en el escenario 'comparacion_consumos'. | C23: 0.9 | D23: The Actual Output over-decomposes the input 'Dime el consumo del aire acondicionado esta semana y compáralo con la semana pasada.' into three intentions, while the Expected Output correctly identifies two. Specifically, the Actual Output creates an explicit intention '@2': 'Dime el consumo del aire acondicionado la semana pasada' classified as 'consumo_basico', which the Expected Output considers implicitly handled by the comparison intention. This indicates a failure in correctly decomposing the input (A1) and adequately inferring implicit intentions (A3) according to the Expected Output reference. While the classifications for the identified intentions are correct and the internal coherence (A4) is maintained, the deviation in decomposition means that criteria A1 and A3 are not fully met, placing the response in the 0-4 range. | E23: Dime el consumo del aire acondicionado esta semana y compáralo con la semana pasada. | F23: Inferencia válida. nueva nota: 0.9
A24: =_xlfn.XLOOKUP(E24,Orden_preguntas!$B:$B,Orden_preguntas!$A:$A) -> 23 | B24: {'@1': {'solicitud': '¿Cuánto consumió mi PC ayer?', 'escenario': 'consumo_basico'}, '@2': {'solicitud': '¿Ha venido aumentando el consumo de mi PC este mes?', 'escenario': 'deteccion_anomalias_tendencias'}} | notas: La primera solicitud busca un valor cuantitativo de consumo registrado para un dispositivo específico (PC) en un periodo explícito (ayer), lo cual encaja en el escenario 'consumo_basico'. La segunda solicitud indaga sobre una tendencia sostenida en el consumo durante un periodo (este mes), lo que implica análisis de patrones temporales y corresponde al escenario 'deteccion_anomalias_tendencias'. | C24: 1 | D24: El modelo descompone correctamente la solicitud del usuario '¿Cuánto consumió mi PC ayer y ha venido aumentando su consumo este mes?' en dos peticiones independientes. No inventa información y las intenciones inferidas en '@1' ('¿Cuánto consumió mi PC ayer?') y '@2' ('¿Ha venido aumentando el consumo de mi PC este mes?') se alinean perfectamente con las del 'Expected Output'. Además, clasifica correctamente cada solicitud en su escenario correspondiente: 'consumo_basico' para la primera y 'deteccion_anomalias_tendencias' para la segunda, lo cual coincide con el 'Expected Output'. Las 'notas' proporcionadas en el 'Actual Output' son claras y coherentes, justificando adecuadamente la asignación de escenarios. | E24: ¿Cuánto consumió mi PC ayer y ha venido aumentando su consumo este mes?
A25: =_xlfn.XLOOKUP(E25,Orden_preguntas!$B:$B,Orden_preguntas!$A:$A) -> 24 | B25: {'@1': {'solicitud': 'Quiero saber el consumo del ventilador ayer.', 'escenario': 'consumo_basico'}, '@2': {'solicitud': 'Quiero saber si hubo algún pico extraño en el consumo ayer.', 'escenario': 'deteccion_anomalias_tendencias'}} | notas: La primera solicitud busca un valor de consumo específico (del ventilador) dentro de un periodo definido (ayer), lo cual encaja en el escenario 'consumo_basico'. La segunda solicitud indaga sobre la existencia de picos o comportamientos anómalos en el consumo, lo cual se ajusta al escenario 'deteccion_anomalias_tendencias'. | C25: 1 | D25: The model correctly decomposes the input 'Quiero saber el consumo del ventilador y si hubo algún pico extraño ayer' into two distinct intentions, '@1' for basic consumption and '@2' for anomaly detection, without inventing information. It accurately infers that 'ayer' applies to both requests and that 'pico extraño' refers to 'consumo'. Both intentions are correctly classified into 'consumo_basico' and 'deteccion_anomalias_tendencias' respectively, aligning with the expected output. The 'notas' field provides clear and consistent reasoning for these classifications, demonstrating strong internal coherence. | E25: Quiero saber el consumo del ventilador y si hubo algún pico extraño ayer.
A26: =_xlfn.XLOOKUP(E26,Orden_preguntas!$B:$B,Orden_preguntas!$A:$A) -> 25 | B26: {'@1': {'solicitud': '¿Cuánto consumió mi casa en noviembre?', 'escenario': 'consumo_basico'}, '@2': {'solicitud': '¿Cómo se compara el consumo de mi casa en noviembre con el de octubre?', 'escenario': 'comparacion_consumos'}} | notas: La primera parte de la solicitud pregunta por el valor de consumo energético registrado en un periodo específico (noviembre), lo cual encaja con el escenario "consumo_basico". La segunda parte busca una comparación directa entre dos periodos (noviembre y octubre), lo cual se alinea con el escenario "comparacion_consumos". | C26: 1 | D26: The model successfully decomposes the input into two independent requests, '@1' and '@2', without inventing any information (A1, A2). The inferred intentions in the actual output's requests, such as '¿Cuánto consumió mi casa en noviembre?' and '¿Cómo se compara el consumo de mi casa en noviembre con el de octubre?', correctly interpret the natural language of the input and align perfectly with the expected output's interpretations (A3). Furthermore, both requests are accurately classified into their respective scenarios, 'consumo_basico' and 'comparacion_consumos', which matches the expected output (B1). The 'notas' field provides a clear and coherent explanation for the decomposition and scenario assignment (A4). | E26: ¿Cuánto consumió mi casa en noviembre y cómo se compara con octubre?
A27: =_xlfn.XLOOKUP(E27,Orden_preguntas!$B:$B,Orden_preguntas!$A:$A) -> 26 | B27: {'@1': {'solicitud': 'Dime el consumo del televisor ayer.', 'escenario': 'consumo_basico'}, '@2': {'solicitud': 'Analiza si su consumo va en aumento.', 'escenario': 'deteccion_anomalias_tendencias'}} | notas: La primera solicitud se enfoca en obtener un valor específico de consumo energético (del televisor) para un periodo definido (ayer), lo cual encaja claramente en el escenario "consumo_basico". La segunda solicitud busca identificar una tendencia (aumento) en el consumo a lo largo del tiempo, lo cual corresponde al escenario "deteccion_anomalias_tendencias", ya que implica análisis de patrones temporales. | C27: 1 | D27: The model correctly decomposes the input into two independent requests, 'Dime el consumo del televisor ayer.' and 'Analiza si su consumo va en aumento.', without inventing any information (A1, A2). The inferred intentions align perfectly with the Expected Output's interpretation, capturing the essence of consulting consumption and analyzing trends (A3). Both requests are accurately classified into their respective scenarios, 'consumo_basico' and 'deteccion_anomalias_tendencias', matching the Expected Output (B1). Furthermore, the 'notas' field in the Actual Output provides clear and coherent justifications for these classifications (A4). | E27: Dime el consumo del televisor ayer y analiza si su consumo va en aumento.
A28: =_xlfn.XLOOKUP(E28,Orden_preguntas!$B:$B,Orden_preguntas!$A:$A) -> 27 | B28: {'@1': {'solicitud': '¿Cuánto consumió la lavadora el sábado?', 'escenario': 'consumo_basico'}, '@2': {'solicitud': '¿El consumo de la lavadora el sábado fue más que el domingo?', 'escenario': 'comparacion_consumos'}} | notas: La primera parte de la consulta pregunta por el consumo registrado de un dispositivo específico (lavadora) en un día determinado (sábado), lo cual encaja con el escenario "consumo_basico" ya que se solicita un valor histórico concreto. La segunda parte introduce una comparación explícita entre dos días (sábado vs domingo), buscando determinar cuál tuvo mayor consumo, lo cual corresponde al escenario "comparacion_consumos". | C28: 1 | D28: The model successfully decomposed the input '¿Cuánto consumió la lavadora el sábado y fue más que el domingo?' into two independent requests without inventing information (A1, A2). The interpretation of these requests, '¿Cuánto consumió la lavadora el sábado?' and '¿El consumo de la lavadora el sábado fue más que el domingo?', accurately reflects the user's intent and aligns semantically with the expected output (A3). Furthermore, both requests were correctly classified into their respective scenarios, 'consumo_basico' and 'comparacion_consumos', which perfectly match the nature of the queries (B1). The 'notas' field provides a clear and coherent explanation for both the decomposition and scenario assignments (A4). | E28: ¿Cuánto consumió la lavadora el sábado y fue más que el domingo?
A29: =_xlfn.XLOOKUP(E29,Orden_preguntas!$B:$B,Orden_preguntas!$A:$A) -> 28 | B29: {'@1': {'solicitud': 'Quiero el consumo del horno este mes.', 'escenario': 'consumo_basico'}, '@2': {'solicitud': 'Quiero saber si hay alguna anomalía en el consumo del horno este mes.', 'escenario': 'deteccion_anomalias_tendencias'}} | notas: La primera solicitud se enfoca en obtener un valor específico de consumo energético del horno dentro de un periodo de tiempo claro (este mes), lo cual encaja en el escenario "consumo_basico". La segunda solicitud busca identificar comportamientos anómalos en el consumo del mismo dispositivo durante el mismo periodo, lo cual corresponde al escenario "deteccion_anomalias_tendencias". | C29: 1 | D29: The model correctly decomposes the input into two independent intentions, 'Quiero el consumo del horno este mes.' and 'Quiero saber si hay alguna anomalía en el consumo del horno este mes.', without inventing information. It accurately infers the implicit context for the anomaly detection, linking it to the oven's consumption this month. Both intentions are correctly classified into their respective scenarios, 'consumo_basico' and 'deteccion_anomalias_tendencias'. The 'notas' field provides clear and consistent reasoning for these classifications, demonstrating strong internal coherence. | E29: Quiero el consumo del horno este mes y saber si hay alguna anomalía.
A30: =_xlfn.XLOOKUP(E30,Orden_preguntas!$B:$B,Orden_preguntas!$A:$A) -> 29 | B30: {'@1': {'solicitud': '¿Cuánto consumió mi nevera ayer?', 'escenario': 'consumo_basico'}, '@2': {'solicitud': 'Compara el consumo de mi nevera con el de la lavadora durante ayer.', 'escenario': 'comparacion_consumos'}, '@3': {'solicitud': 'Dime si hubo picos raros en el consumo de mi nevera o de la lavadora ayer.', 'escenario': 'deteccion_anomalias_tendencias'}} | notas: La solicitud original se desglosa en tres intenciones claramente diferenciadas: (1) Consultar el consumo histórico de un dispositivo específico (la nevera) durante un día definido, lo cual se ajusta al escenario "consumo_basico". (2) Comparar el consumo entre dos dispositivos (nevera vs. lavadora) en un periodo común, encajando en "comparacion_consumos". (3) Evaluar la presencia de comportamientos anómalos en el consumo de dichos dispositivos, lo que corresponde a "deteccion_anomalias_tendencias". | C30: 1 | D30: The model correctly decomposes the input into three individual intentions, aligning with A1. It does not invent any information (A2) and accurately infers implicit details like the time frame ('ayer') for the comparison and anomaly detection, and that anomaly detection applies to both devices (A3). All three intentions are correctly classified into their respective scenarios ('consumo_basico', 'comparacion_consumos', 'deteccion_anomalias_tendencias'), demonstrating correct B1 classification. Furthermore, the 'notas' field provides clear and consistent reasoning for each decomposition and classification, ensuring internal coherence (A4). The output fully meets all criteria for the highest score range. | E30: ¿Cuánto consumió mi nevera ayer, compárala con la lavadora y dime si hay picos raros?
A31: =_xlfn.XLOOKUP(E31,Orden_preguntas!$B:$B,Orden_preguntas!$A:$A) -> 30 | B31: {'@1': {'solicitud': 'Dime el consumo del aire acondicionado ayer.', 'escenario': 'consumo_basico'}, '@2': {'solicitud': 'Dime si eso significa que soy irresponsable.', 'escenario': 'entrada_inadmisible'}} | notas: La primera solicitud busca un valor de consumo específico (del aire acondicionado) para un periodo claramente definido (ayer), encajando en el escenario 'consumo_basico'. La segunda solicitud tiene un componente subjetivo (evaluar si el usuario es irresponsable) que no se relaciona con ninguna funcionalidad del sistema de gestión energética, por lo tanto se clasifica como 'entrada_inadmisible'. | C31: 1 | D31: The model correctly decomposes the input into two distinct intentions, 'Dime el consumo del aire acondicionado ayer' and 'Dime si eso significa que soy irresponsable', without inventing information. Both intentions are accurately classified into 'consumo_basico' and 'entrada_inadmisible' respectively, aligning with the Expected Output. The 'notas' field provides clear and consistent reasoning for each classification, demonstrating strong internal coherence. All criteria (A1-A4 and B1) are met. | E31: Dime el consumo del aire acondicionado ayer y dime si eso significa que soy irresponsable.
A32: =_xlfn.XLOOKUP(E32,Orden_preguntas!$B:$B,Orden_preguntas!$A:$A) -> 31 | B32: {'@1': {'solicitud': 'Dime el consumo de mi nevera ayer.', 'escenario': 'consumo_basico'}, '@2': {'solicitud': 'Compara el consumo de mi nevera ayer con el consumo del sábado pasado.', 'escenario': 'comparacion_consumos'}} | notas: La primera solicitud pregunta por un valor de consumo energético registrado (ayer) para un dispositivo específico (la nevera), sin realizar comparaciones ni análisis adicionales, por lo que encaja en el escenario 'consumo_basico'. La segunda solicitud busca comparar dos valores de consumo (ayer vs. sábado pasado) para el mismo dispositivo, utilizando un lenguaje comparativo explícito, lo cual corresponde al escenario 'comparacion_consumos'. | C32: 1 | D32: The model correctly decomposes the input 'Dime el consumo de mi nevera ayer y luego compáralo con el consumo del sábado pasado' into two independent requests, '@1': 'Dime el consumo de mi nevera ayer.' and '@2': 'Compara el consumo de mi nevera ayer con el consumo del sábado pasado.', without inventing any information. The inferred intentions and details align perfectly with the Expected Output's interpretation. Furthermore, both requests are correctly classified into their respective scenarios, 'consumo_basico' and 'comparacion_consumos', which aligns with the Expected Output and the explicit comparative language in the input. The 'notas' field provides a clear and coherent explanation for both the decomposition and scenario assignments, demonstrating a strong understanding of the user's intent. | E32: Dime el consumo de mi nevera ayer y luego compáralo con el consumo del sábado pasado.
A33: =_xlfn.XLOOKUP(E33,Orden_preguntas!$B:$B,Orden_preguntas!$A:$A) -> 32 | B33: {'@1': {'solicitud': 'Consultar el consumo energético total de la vivienda durante el mes actual (enero de 2026).', 'escenario': 'consumo_basico'}, '@2': {'solicitud': 'Comparar el consumo energético del mes actual (enero de 2026) con el del mes inmediatamente anterior (diciembre de 2025) para determinar si hubo un aumento.', 'escenario': 'comparacion_consumos'}} | notas: La primera solicitud se enfoca en obtener un valor específico de consumo energético para un periodo definido (enero de 2026), lo cual corresponde al escenario 'consumo_basico'. La segunda solicitud busca comparar dos periodos distintos para identificar una diferencia relativa, clasificándose como 'comparacion_consumos'. | C33: 0.3 | D33: The model correctly decomposes the input into two independent intentions (A1) and assigns the correct scenario classifications ('consumo_basico', 'comparacion_consumos') to each (B1). It also maintains internal coherence in its 'notas' field (A4). However, the model invents specific dates ('enero de 2026', 'diciembre de 2025') that are not present in the input's 'este mes' and 'mes pasado', which constitutes inventing information not provided (A2). This violation of A2 places the response in the 0-4 range of the rubric. | E33: Primero quiero saber cuánto consumió mi casa este mes y después si aumentó respecto al mes pasado.
A34: =_xlfn.XLOOKUP(E34,Orden_preguntas!$B:$B,Orden_preguntas!$A:$A) -> 33 | B34: {'@1': {'solicitud': 'Dime el consumo del aire acondicionado la semana pasada.', 'escenario': 'consumo_basico'}, '@2': {'solicitud': 'Analiza si hubo anomalías en el consumo del aire acondicionado la semana pasada.', 'escenario': 'deteccion_anomalias_tendencias'}} | notas: La primera solicitud busca un valor cuantitativo específico (consumo del aire acondicionado) dentro de un periodo de tiempo claramente inferible (la semana pasada), lo cual encaja con el escenario 'consumo_basico'. La segunda solicitud pide identificar comportamientos anómalos o irregulares en el consumo energético durante un periodo definido, lo cual corresponde al escenario 'deteccion_anomalias_tendencias'. | C34: 1 | D34: The model correctly decomposes the input into two independent intentions, 'Dime el consumo del aire acondicionado la semana pasada' and 'Analiza si hubo anomalías en el consumo del aire acondicionado la semana pasada', without inventing information. It accurately infers the context for the second request from the first. Both intentions are correctly classified into 'consumo_basico' and 'deteccion_anomalias_tendencias' respectively, aligning with the expected output. The 'notas' field provides clear and consistent reasoning for these classifications, demonstrating strong internal coherence. | E34: Dime el consumo del aire acondicionado la semana pasada y luego analiza si hubo anomalías.
A35: =_xlfn.XLOOKUP(E35,Orden_preguntas!$B:$B,Orden_preguntas!$A:$A) -> 34 | B35: {'@1': {'solicitud': 'Obtener el consumo del televisor ayer', 'escenario': 'consumo_basico'}, '@2': {'solicitud': 'Obtener el consumo del televisor hoy', 'escenario': 'consumo_basico'}, '@3': {'solicitud': 'Comparar el consumo del televisor de ayer con el de hoy', 'escenario': 'comparacion_consumos'}} | notas: La solicitud inicial abarca tanto la obtención de datos de consumo como una comparación. Se divide en tres partes: dos solicitudes específicas para obtener el consumo del televisor en dos días distintos (ayer y hoy), clasificadas como 'consumo_basico' porque implican consultar valores históricos puntuales. La tercera parte corresponde explícitamente a una comparación entre dos periodos, por lo que se clasifica como 'comparacion_consumos'. | C35: 1 | D35: El modelo descompone correctamente la solicitud del usuario 'Obtén el consumo del televisor ayer y compáralo con el de hoy' en tres peticiones independientes, sin inventar información (A1, A2). La interpretación de las intenciones en las solicitudes descompuestas ('Obtener el consumo del televisor ayer', 'Obtener el consumo del televisor hoy', 'Comparar el consumo del televisor de ayer con el de hoy') se alinea perfectamente con la interpretación del `Expected Output` (A3). Además, cada solicitud está correctamente clasificada en su escenario correspondiente ('consumo_basico' para las consultas individuales y 'comparacion_consumos' para la comparación), coincidiendo con el `Expected Output` (B1). Finalmente, el campo 'notas' del `Actual Output` es claro y coherente, explicando la lógica de la descomposición y clasificación (A4). | E35: Obtén el consumo del televisor ayer y compáralo con el de hoy.
... A47: =_xlfn.XLOOKUP(E47,Orden_preguntas!$B:$B,Orden_preguntas!$A:$A) -> 46 | B47: {'@1': {'solicitud': 'Consultar el consumo energético registrado ayer para la nevera y el televisor.', 'escenario': 'consumo_basico'}, '@2': {'solicitud': 'Determinar cuál de los dos dispositivos, la nevera o el televisor, tuvo un mayor consumo energético ayer.', 'escenario': 'comparacion_consumos'}} | notas: La primera parte de la solicitud pregunta por valores históricos de consumo energético para dos dispositivos específicos (nevera y televisor) en un periodo definido (ayer), lo cual encaja en el escenario 'consumo_basico'. La segunda parte busca identificar cuál de los dos dispositivos consumió más energía en el mismo periodo, lo cual implica una comparación directa entre ambos, por lo tanto se asigna al escenario 'comparacion_consumos'. | C47: 0.8 | D47: The model correctly identifies the two main intentions from the input: consulting consumption and comparing consumption. It assigns the correct scenarios ('consumo_basico' and 'comparacion_consumos') for these intentions, which aligns with criterion B1. No information is invented (A2), and the 'notas' field is clear and coherent (A4). The primary shortcoming is in the granularity of decomposition (A1) and alignment with the Expected Output's interpretation (A3), as it combines the consumption queries for 'nevera' and 'televisor' into a single request, whereas the Expected Output separates them into two distinct, individual requests. However, this is a minor deviation in decomposition rather than a fundamental failure or misinterpretation, and the overall understanding and correct scenario classification warrant a high score. | E47: ¿Cuánto consumieron la nevera y el televisor ayer y cuál fue mayor?
A48: =_xlfn.XLOOKUP(E48,Orden_preguntas!$B:$B,Orden_preguntas!$A:$A) -> 47 | B48: {'@1': {'solicitud': 'Obtener el consumo total de la casa durante el año en curso (2026) hasta la fecha actual.', 'escenario': 'consumo_basico'}, '@2': {'solicitud': 'Obtener el consumo total de la casa durante el mismo periodo del año anterior (2025) para realizar una comparación con el año actual.', 'escenario': 'comparacion_consumos'}, '@3': {'solicitud': 'Identificar días con picos o valores anómalos de consumo energético dentro del año en curso (2026).', 'escenario': 'deteccion_anomalias_tendencias'}} | notas: La solicitud se desglosa en tres partes para alinearse con los escenarios específicos del sistema. La primera parte busca simplemente el valor total del consumo en un periodo determinado, lo cual encaja con "consumo_basico". La segunda parte implica una comparación entre dos periodos temporales consecutivos, identificando si hubo un aumento, lo que corresponde a "comparacion_consumos". La tercera parte busca identificar días anómalos dentro del periodo, lo cual se ajusta al escenario de "deteccion_anomalias_tendencias". | C48: 0.3 | D48: The model correctly decomposes the input into three distinct intentions (A1) and infers the implicit need for comparison for 'si ha aumentado este año' (A3). It does not invent information that distorts the core intent (A2), and its 'notas' field provides clear and consistent reasoning for its classifications (A4). However, the classification for the second intention, 'si ha aumentado este año', is given as 'comparacion_consumos' in the Actual Output, while the Expected Output classifies the equivalent intention ('Analizar la tendencia anual') as 'deteccion_anomalias_tendencias'. This constitutes one incorrect scenario classification (B1) when compared against the Expected Output, placing the response in the 5-7 range of the rubric. | E48: Quiero saber el consumo total de la casa, si ha aumentado este año y si hubo días anómalos. | F48: el modelo inventa información y referencia fechas de la nada. nueva nota: 0.3
A49: =_xlfn.XLOOKUP(E49,Orden_preguntas!$B:$B,Orden_preguntas!$A:$A) -> 48 | B49: {'@1': {'solicitud': 'Dime el consumo de mi lavadora el fin de semana', 'escenario': 'consumo_basico'}, '@2': {'solicitud': 'Compara el consumo de mi lavadora con el horno durante el fin de semana', 'escenario': 'comparacion_consumos'}, '@3': {'solicitud': 'Revisa si hubo picos de consumo en mi lavadora durante el fin de semana', 'escenario': 'deteccion_anomalias_tendencias'}} | notas: 1. La primera parte solicita el valor del consumo de un dispositivo (lavadora) en un periodo específico (fin de semana), sin realizar comparaciones ni análisis adicionales. Esto se ajusta al escenario 'consumo_basico'. 2. La segunda parte compara explícitamente el consumo de dos dispositivos (lavadora y horno) en un periodo definido, lo cual encaja claramente en el escenario 'comparacion_consumos'. 3. La tercera parte busca identificar irregularidades o picos en el consumo de un dispositivo específico, lo cual es propio del escenario 'deteccion_anomalias_tendencias'. | C49: 0.8 | D49: The model correctly decomposes the input into three independent requests (A1) and does not invent information (A2). The 'notas' field is clear and coherent (A4), and the scenario assignments (B1) are correct based on the model's interpretation of each request. However, the model fails to adequately infer implicit intentions for the third request (A3). The input 'revisa si hubo picos' implicitly refers to both the 'lavadora' and 'horno' given the preceding comparison, but the Actual Output narrows the scope of peak detection only to the 'lavadora', unlike the Expected Output which correctly includes both devices. This failure in adequately inferring implicit intentions means that the 'A1-A4 correctos' condition for scores 5 and above is not met, placing the response in the 0-4 range due to insufficient semantic quality (A3) regarding the scope of the request. | E49: Dime el consumo de mi lavadora el fin de semana, compárala con el horno y revisa si hubo picos. | F49: Se considera que el modelo hizo una interpretación válida de la solicitud del usuario. nueva nota: 0.8
A50: =_xlfn.XLOOKUP(E50,Orden_preguntas!$B:$B,Orden_preguntas!$A:$A) -> 49 | B50: {'@1': {'solicitud': '¿Cuánto consumió el aire acondicionado ayer?', 'escenario': 'consumo_basico'}, '@2': {'solicitud': '¿Cómo se compara el consumo del aire acondicionado de ayer con la semana pasada?', 'escenario': 'comparacion_consumos'}, '@3': {'solicitud': '¿Qué tendencia tiene el consumo del aire acondicionado?', 'escenario': 'deteccion_anomalias_tendencias'}} | notas: La solicitud 1 corresponde al escenario 'consumo_basico' porque se centra en consultar un valor específico de consumo energético (del aire acondicionado) en un periodo definido (ayer), sin realizar análisis adicionales. La solicitud 2 encaja en 'comparacion_consumos' ya que explícitamente solicita una comparación entre dos periodos de tiempo (ayer vs. la semana pasada). La solicitud 3 pertenece a 'deteccion_anomalias_tendencias' porque busca identificar patrones o tendencias en el consumo del dispositivo, lo cual implica un análisis temporal de los datos. | C50: 1 | D50: The model successfully decomposes the input into three independent requests, accurately reflecting the user's intentions without inventing any information. The interpretation of each request aligns perfectly with the expected output's underlying meaning. Furthermore, each decomposed request is correctly assigned to its respective scenario ('consumo_basico', 'comparacion_consumos', 'deteccion_anomalias_tendencias'), and the 'notas' field provides clear and coherent justifications for these assignments, demonstrating a complete understanding of the input and context. | E50: ¿Cuánto consumió el aire acondicionado ayer, cómo se compara con la semana pasada y qué tendencia tiene?
A51: =_xlfn.XLOOKUP(E51,Orden_preguntas!$B:$B,Orden_preguntas!$A:$A) -> 50 | B51: {'@1': {'solicitud': 'Dime el consumo de mi nevera ayer', 'escenario': 'consumo_basico'}, '@2': {'solicitud': 'Compara el consumo de mi nevera con la lavadora ayer', 'escenario': 'comparacion_consumos'}, '@3': {'solicitud': 'Basado en el consumo de mi nevera y la lavadora ayer, estima cuánto dinero podría ahorrar en un mes para ver si me alcanza para un viaje', 'escenario': 'prediccion_estimacion'}} | notas: La primera solicitud pide un valor específico de consumo (de la nevera) para un día concreto (ayer), lo cual encaja con el escenario "consumo_basico". La segunda solicitud compara el consumo entre dos dispositivos (nevera y lavadora) para el mismo periodo, lo que corresponde al escenario "comparacion_consumos". La tercera solicitud implica una estimación futura de ahorro económico basado en datos actuales para un propósito específico (viaje), lo cual encaja con el escenario "prediccion_estimacion". | C51: 0.6 | D51: The model correctly decomposes the first two intentions from the input and assigns them the correct scenario classifications ('consumo_basico' and 'comparacion_consumos'). The reasoning in the 'notas' field is internally consistent with these classifications. However, the model incorrectly classifies the third intention, 'dime si con eso ya puedo ahorrar para irme de viaje'. It interprets this as a 'prediccion_estimacion' and adds details like 'en un mes', which is an over-interpretation and implies a system capability not present. The Expected Output correctly identifies this as an 'entrada_inadmisible', indicating it's outside the system's domain. This misclassification of a key request (B1 incorrect) places the response in the 5-7 range. | E51: Dime el consumo de mi nevera ayer, compárala con la lavadora y dime si con eso ya puedo ahorrar para irme de viaje.

Sheet deepseek_r1t2_chimera_671b
A1: ID_PREGUNTA | B1: Respuesta_Modelo | C1: Puntaje_Calidad | D1: Razon_del_Juez | E1: Pregunta
A2: =_xlfn.XLOOKUP(E2,Orden_preguntas!$B:$B,Orden_preguntas!$A:$A) -> 1 | B2: {'@1': {'solicitud': '¿Cuánto consumió mi televisor ayer en la noche?', 'escenario': 'consumo_basico'}} | notas: Se asignó el escenario 'consumo_basico' porque: 1. La solicitud busca un valor de consumo histórico para un dispositivo específico (televisor) 2. El periodo temporal está explícitamente definido ("ayer en la noche") 3. No implica comparación, detección de patrones ni predicción, sino un dato puntual 4. Cumple con los criterios de 'usar_si' para consumo_basico según su descripción | C2: 0.9 | D2: The model correctly decomposes the input into a single intention (A1) without inventing information (A2). It accurately classifies the intention as 'consumo_basico', matching the Expected Output (B1). The 'notas' field provides clear and consistent reasoning for this classification, demonstrating strong internal coherence (A4). The model correctly infers the explicit intention (A3). The only minor difference is that the 'solicitud' field in the Actual Output is a direct copy of the input, whereas the Expected Output rephrases it slightly, but this does not detract from the correctness of the decomposition or classification. | E2: ¿Cuánto consumió mi televisor ayer en la noche?
A3: =_xlfn.XLOOKUP(E3,Orden_preguntas!$B:$B,Orden_preguntas!$A:$A) -> 2 | B3: {'@1': {'solicitud': 'Dime el consumo de mi lavadora el lunes pasado', 'escenario': 'consumo_basico'}} | notas: Se seleccionó el escenario 'consumo_basico' porque: - La solicitud busca un valor de consumo histórico específico (lavadora) - Se especifica un período temporal concreto (lunes pasado) - No hay elementos comparativos, de análisis de tendencias o predicciones - La respuesta esperada es un dato cuantitativo puntual de consumo energético | C3: 1 | D3: The model correctly decomposes the input into a single request without inventing information (A1, A2). The inferred intention in the 'solicitud' field, 'Dime el consumo de mi lavadora el lunes pasado', accurately reflects the user's query and aligns perfectly with the 'Expected Output's interpretation (A3). Furthermore, the assigned scenario 'consumo_basico' is correct and matches the 'Expected Output' (B1). The 'notas' field provides a clear, coherent, and detailed justification for the scenario selection, consistent with the request for a specific historical consumption value for the washing machine on 'lunes pasado' (A4). | E3: Dime el consumo de mi lavadora el lunes pasado.
A4: =_xlfn.XLOOKUP(E4,Orden_preguntas!$B:$B,Orden_preguntas!$A:$A) -> 3 | B4: {'@1': {'solicitud': 'Obtener el consumo energético total del hogar completo durante el mes de marzo de 2024 en kWh', 'escenario': 'consumo_basico'}} | notas: Escenario seleccionado: consumo_basico Razonamiento: - El usuario solicita un valor histórico de consumo específico para toda la casa - Se especifica un periodo temporal claro (marzo 2024) - No involucra comparaciones, análisis de patrones o predicciones futuras - La respuesta esperada es un valor cuantitativo único - Cumple con 3 criterios de 'usar_si' del escenario: consulta de valores históricos + periodo explícito + respuesta cuantitativa | C4: 1 | D4: The model correctly decomposes the input into a single, independent intention (A1) without inventing any information (A2). It accurately classifies the intention as 'consumo_basico', which aligns perfectly with the Expected Output (B1). The 'notas' field provides a clear, detailed, and consistent reasoning for the chosen scenario, demonstrating strong internal coherence (A4). The `solicitud` also correctly infers the user's implicit intent (A3) by specifying 'en kWh' and 'hogar completo', which are reasonable elaborations of 'consumo total de la casa'. | E4: ¿Cuál fue el consumo total de la casa durante marzo de 2024?
A5: =_xlfn.XLOOKUP(E5,Orden_preguntas!$B:$B,Orden_preguntas!$A:$A) -> 4 | B5: {'@1': {'solicitud': 'Quiero saber cuánta energía gastó mi computador hoy', 'escenario': 'consumo_basico'}} | notas: Se clasifica en 'consumo_basico' porque: 1. El usuario solicita valores históricos de consumo energético para un dispositivo específico (computador) 2. La consulta incluye un intervalo temporal explícito ("hoy") 3. La respuesta esperada es un valor cuantitativo puntual 4. No existen elementos comparativos, análisis de tendencias ni requerimientos predictivos 5. Es una consulta autocontenida que requiere acceso directo a datos registrados | C5: 1 | D5: The model correctly decomposes the single request from the input 'Quiero saber cuánta energía gastó mi computador hoy', accurately interpreting the user's intention without inventing information (A1, A2, A3). It correctly assigns the 'consumo_basico' scenario, which aligns with the Expected Output (B1). Furthermore, the 'notas' field is exceptionally clear and coherent, providing a detailed and accurate justification for the scenario classification (A4), demonstrating a thorough understanding of the request. | E5: Quiero saber cuánta energía gastó mi computador hoy.
A6: =_xlfn.XLOOKUP(E6,Orden_preguntas!$B:$B,Orden_preguntas!$A:$A) -> 5 | B6: {'@1': {'solicitud': "Obtener el valor de consumo energético del dispositivo 'aire acondicionado' durante el período comprendido entre el inicio y el final del fin de semana pasado.", 'escenario': 'consumo_basico'}} | notas: Se clasifica en 'consumo_basico' porque: 1. Solicita un dato de consumo histórico específico (verbo "consumió" en pasado). 2. Especifica un intervalo temporal claro ("fin de semana pasado") que puede inferirse operacionalmente. 3. La respuesta esperada es un valor cuantitativo puntual sin análisis comparativo ni procesamiento predictivo. 4. No involucra comparaciones, detección de patrones o escenarios hipotéticos. | C6: 1 | D6: The model accurately decomposes the single request from the input '¿Cuánto consumió el aire acondicionado el fin de semana pasado?'. It correctly interprets the user's intention to 'Obtener el valor de consumo energético del dispositivo 'aire acondicionado' durante el período comprendido entre el inicio y el final del fin de semana pasado', which aligns well with the expected output's interpretation. No information is invented. Furthermore, the model correctly classifies the request into the 'consumo_basico' scenario, matching the expected output, and provides a detailed, coherent, and accurate justification in the 'notas' field for this classification. | E6: ¿Cuánto consumió el aire acondicionado el fin de semana pasado?
A7: =_xlfn.XLOOKUP(E7,Orden_preguntas!$B:$B,Orden_preguntas!$A:$A) -> 6 | B7: {'@1': {'solicitud': "Obtener el consumo energético registrado del dispositivo 'ventilador' durante el día de ayer", 'escenario': 'consumo_basico'}} | notas: Se selecciona el escenario 'consumo_basico' porque la solicitud cumple con: - Consulta valores de consumo energético histórico para un dispositivo específico - Periodo temporal explícitamente definido (ayer) - No involucra comparaciones, análisis de patrones ni proyecciones futuras - La respuesta esperada es un valor cuantitativo específico para el período solicitado | C7: 1 | D7: The model successfully decomposed the input into a single, independent request without inventing information. The inferred intention, 'Obtener el consumo energético registrado del dispositivo 'ventilador' durante el día de ayer', accurately reflects the input 'Muéstrame el consumo del ventilador el día de ayer' and aligns perfectly with the expected output's interpretation. Furthermore, the 'consumo_basico' scenario was correctly assigned, and the 'notas' field provided a clear, coherent, and detailed justification for this classification, fulfilling all A1-A4 and B1 criteria. | E7: Muéstrame el consumo del ventilador el día de ayer.
A8: =_xlfn.XLOOKUP(E8,Orden_preguntas!$B:$B,Orden_preguntas!$A:$A) -> 7 | B8: {'@1': {'solicitud': '¿Cuál fue el consumo energético de mi horno el 15 de noviembre?', 'escenario': 'consumo_basico'}} | notas: Se categoriza en 'consumo_basico' porque: 1. La consulta solicita un valor histórico de consumo energético (de un dispositivo específico). 2. Se especifica un periodo temporal concreto (15 de noviembre). 3. No requiere comparaciones, análisis de tendencias ni estimaciones futuras. 4. La respuesta esperada es un dato cuantitativo puntual. | C8: 1 | D8: The model accurately identifies the single user intention from the input '¿Cuál fue el consumo energético de mi horno el 15 de noviembre?'. It correctly classifies this intention under the 'consumo_basico' scenario, matching the Expected Output. Furthermore, the 'notas' field provides a clear and coherent explanation for this classification, detailing why the request fits the 'consumo_basico' criteria (historical, specific date, no complex analysis). | E8: ¿Cuál fue el consumo energético de mi horno el 15 de noviembre?
A9: =_xlfn.XLOOKUP(E9,Orden_preguntas!$B:$B,Orden_preguntas!$A:$A) -> 8 | B9: {'@1': {'solicitud': 'Dime cuántos kWh consumió mi casa la semana pasada.', 'escenario': 'consumo_basico'}} | notas: El escenario 'consumo_basico' fue seleccionado porque: - La solicitud busca específicamente un valor cuantitativo de consumo energético histórico para el hogar completo. - Incluye un intervalo temporal explícito y delimitado ("la semana pasada"). - No involucra comparaciones, análisis de patrones o estimaciones futuras, solo requiere recuperar un dato registrado. | C9: 1 | D9: The model correctly decomposes the input into a single, independent intention without inventing information. It accurately classifies the intention as 'consumo_basico', which aligns with the request 'Dime cuántos kWh consumió mi casa la semana pasada.' and matches the Expected Output. Furthermore, the 'notas' field provides clear and consistent reasoning for the chosen scenario, demonstrating strong internal coherence. | E9: Dime cuántos kWh consumió mi casa la semana pasada.
A10: =_xlfn.XLOOKUP(E10,Orden_preguntas!$B:$B,Orden_preguntas!$A:$A) -> 9 | B10: {'@1': {'solicitud': "Obtener el consumo energético (en kWh) del dispositivo 'nevera' durante el periodo completo del mes de enero del año actual.", 'escenario': 'consumo_basico'}} | notas: Se seleccionó el escenario 'consumo_basico' porque: 1. La consulta solicita explícitamente un valor de consumo histórico para un dispositivo específico. 2. Se menciona un periodo temporal claramente definido (mes de enero). 3. No existen elementos de comparación, detección de patrones o estimaciones futuras en la solicitud. 4. La intención se alinea con la descripción de acceso a datos puntuales/históricos en el escenario definido. | C10: 0.8 | D10: The model correctly decomposes the input into a single request (A1) and accurately classifies it under the 'consumo_basico' scenario (B1), aligning with the Expected Output. The 'notas' field is clear and coherent, providing a strong justification for the scenario choice (A4). The core intention of querying fridge consumption in January is correctly inferred. However, the 'solicitud' in the Actual Output includes 'del año actual', which is not explicitly present in the Input nor in the Expected Output, representing a minor invention of information (A2) and a slight deviation from the Expected Output's interpretation (A3). This prevents a perfect score. | E10: ¿Cuánto consumió mi nevera durante el mes de enero?
A11: =_xlfn.XLOOKUP(E11,Orden_preguntas!$B:$B,Orden_preguntas!$A:$A) -> 10 | B11: {'@1': {'solicitud': 'Determinar el nivel de felicidad de una casa en relación con su consumo energético de ayer', 'escenario': 'entrada_inadmisible'}} | notas: La consulta utiliza un concepto metafórico ("felicidad de la casa") que no corresponde al dominio del análisis de consumo energético. El sistema no tiene capacidad para interpretar estados emocionales/psicológicos asociados a estructuras físicas. Ningún escenario de entrada admisible (focalizados en datos cuantitativos, comparaciones, anomalías o predicciones) puede procesar esta solicitud. | C11: 1 | D11: El modelo descompone correctamente la solicitud del usuario en una única intención, sin inventar información. La clasificación del escenario como 'entrada_inadmisible' es precisa, ya que la consulta sobre la 'felicidad de la casa' no corresponde al dominio del análisis energético. La explicación en las 'notas' es clara, coherente y justifica adecuadamente la clasificación, alineándose perfectamente con el comportamiento esperado para una entrada de este tipo. | E11: ¿Qué tan feliz estuvo mi casa ayer con el consumo de energía?
A12: =_xlfn.XLOOKUP(E12,Orden_preguntas!$B:$B,Orden_preguntas!$A:$A) -> 11 | B12: {'@1': {'solicitud': 'Consultar el consumo energético de la nevera durante el día de ayer (fecha específica)', 'escenario': 'consumo_basico'}, '@2': {'solicitud': 'Consultar el consumo energético de la lavadora durante el día de ayer (fecha específica)', 'escenario': 'consumo_basico'}} | notas: Se identificaron dos solicitudes independientes en el mismo input: 1. Solicitud de consumo de nevera ayer: Es una consulta histórica específica con intervalo temporal definido (ayer), correspondiente a consumo_basico. 2. Solicitud de consumo de lavadora ayer: Mismo patrón que la anterior, consulta puntual con periodo temporal explícito, clasificada en consumo_basico. Ambas peticiones cumplen con las condiciones de 'consumo_basico': solicitan valores históricos específicos sin análisis comparativo ni detección de patrones. | C12: 0.9 | D12: The model correctly decomposes the input into two independent requests (A1) and assigns the correct 'consumo_basico' scenario to both, aligning with the Expected Output (B1). The inferred intentions are accurate, and no information is invented (A2). The 'notas' field is clear and coherent (A4). The only minor deviation is the addition of '(fecha específica)' in the 'solicitud' field of the Actual Output, which, while not present in the Expected Output, does not fundamentally alter the correct interpretation of the input (A3). | E12: Dime el consumo de mi nevera ayer y el consumo de mi lavadora ayer.
A13: =_xlfn.XLOOKUP(E13,Orden_preguntas!$B:$B,Orden_preguntas!$A:$A) -> 12 | B13: {'@1': {'solicitud': 'Consultar el consumo energético del televisor el sábado pasado', 'escenario': 'consumo_basico'}, '@2': {'solicitud': 'Consultar el consumo energético del computador el sábado pasado', 'escenario': 'consumo_basico'}} | notas: Se categoriza como 'consumo_basico' porque: 1. El usuario solicita valores de consumo históricos específicos para dispositivos concretos 2. Incluye un periodo temporal definido (sábado pasado) 3. No se requiere comparación, análisis de patrones ni proyecciones futuras 4. La respuesta esperada son valores cuantitativos puntuales para cada dispositivo 5. Ambas solicitudes cumplen con los criterios del escenario: peticiones autocontenidas de datos ya registrados | C13: 1 | D13: El modelo descompone correctamente la solicitud del usuario en dos peticiones independientes para el televisor y el computador, sin inventar información (A1, A2). La interpretación de las intenciones y los detalles de las solicitudes coincide perfectamente con el 'Expected Output' (A3). Además, clasifica ambas solicitudes correctamente bajo el escenario 'consumo_basico', lo cual se alinea con el 'Expected Output' (B1). Las 'notas' del 'Actual Output' son claras, coherentes y proporcionan una justificación detallada y precisa para la categorización, lo que refuerza la calidad semántica (A4). | E13: ¿Cuánto consumieron el televisor y el computador el sábado pasado?
... A51: =_xlfn.XLOOKUP(E51,Orden_preguntas!$B:$B,Orden_preguntas!$A:$A) -> 50 | B51: {'@1': {'solicitud': 'Obtener el consumo energético de la nevera durante el día anterior.', 'escenario': 'consumo_basico'}, '@2': {'solicitud': 'Comparar el consumo energético de la nevera con el de la lavadora durante el mismo periodo temporal.', 'escenario': 'comparacion_consumos'}, '@3': {'solicitud': 'Evaluar si el ahorro derivado de los consumos detectados permite financiar un viaje, requiriendo una proyección económica basada en datos energéticos.', 'escenario': 'prediccion_estimacion'}} | notas: - **@1**: Clasificado como 'consumo_basico' porque se solicita un valor histórico puntual con un intervalo temporal explícito ("ayer"). - **@2**: Clasificado como 'comparacion_consumos' por requerir una comparación directa entre dos dispositivos usando términos comparativos implícitos ("compárala"). - **@3**: Clasificado como 'prediccion_estimacion' al implicar una estimación económica futura basada en patrones de consumo. Aunque el escenario financiero excede el dominio energético, se asigna esta categoría al requerir una proyección hipotética a partir de datos existentes. | C51: 0.6 | D51: The model correctly decomposes the input into three independent requests and accurately interprets the user's intentions for all of them (A1-A4). Requests @1 and @2 are correctly classified as 'consumo_basico' and 'comparacion_consumos' respectively, aligning with the Expected Output. However, request @3, 'Evaluar si el ahorro derivado de los consumos detectados permite financiar un viaje', is incorrectly classified as 'prediccion_estimacion'. The Expected Output correctly identifies this as 'entrada_inadmisible' because it falls outside the system's domain, a point even acknowledged in the Actual Output's 'notas' ('Aunque el escenario financiero excede el dominio energético'). This single misclassification of a scenario (B1) places the score in the 5-7 range. | E51: Dime el consumo de mi nevera ayer, compárala con la lavadora y dime si con eso ya puedo ahorrar para irme de viaje.

Sheet deepseek_R1_8b
A1: ID_PREGUNTA | B1: Respuesta_Modelo | C1: Puntaje_Calidad | D1: Razon_del_Juez | E1: Pregunta
A2: =_xlfn.XLOOKUP(E2,Orden_preguntas!$B:$B,Orden_preguntas!$A:$A) -> 1 | B2: {'@1': {'solicitud': "Consultar el consumo energético del televisor en el periodo 'ayer en la noche'", 'escenario': 'consumo_basico'}} | notas: """ La solicitud del usuario es consultar el consumo energético de un dispositivo específico (televisor) durante un periodo temporal explícito (ayer en la noche). Esto se ajusta perfectamente al escenario de consumo_basico, ya que: - La intención principal es acceder a datos históricos de consumo - Se especifica explícitamente el periodo de tiempo - Se busca una respuesta cuantitativa única para ese dispositivo y periodo No se mencionan comparaciones, análisis de tendencias o predicciones, por lo que el escenario más adecuado es el de consumo_basico. """ | C2: 1 | D2: The model correctly decomposes the single input request into one independent request, aligning perfectly with A1 and A2. The inferred intention in the 'solicitud' field, 'Consultar el consumo energético del televisor en el periodo 'ayer en la noche'', accurately interprets the input and closely matches the 'Expected Output's interpretation, fulfilling A3. Furthermore, the assigned scenario 'consumo_basico' is correct for the query '¿Cuánto consumió mi televisor ayer en la noche?', satisfying B1. The 'notas' field provides a clear, coherent, and well-reasoned explanation for the scenario choice, meeting A4. All evaluation criteria are fully met. | E2: ¿Cuánto consumió mi televisor ayer en la noche?
A3: =_xlfn.XLOOKUP(E3,Orden_preguntas!$B:$B,Orden_preguntas!$A:$A) -> 2 | B3: {'@1': {'solicitud': 'Dime el consumo de mi lavadora el lunes pasado.', 'escenario': 'consumo_basico'}} | notas: { "razonamiento": "La solicitud se clasifica en el escenario 'consumo_basico' porque el usuario solicita un valor de consumo energético histórico específico (lavadora) con un periodo de tiempo explícito (lunes pasado), lo que coincide con la definición de consumo_basico que busca acceder a datos históricos puntuales sin comparaciones ni análisis adicionales." } | C3: 1 | D3: The model correctly decomposes the input 'Dime el consumo de mi lavadora el lunes pasado.' into a single intention, matching the expected output's intent (A1, A2). The scenario classification 'consumo_basico' is accurate and aligns with the expected output (B1). The reasoning provided in the 'notas' field is clear, consistent, and correctly justifies the classification based on the request for specific historical energy consumption data, demonstrating strong internal coherence (A4). No information was invented, and implicit intentions were handled correctly (A3). | E3: Dime el consumo de mi lavadora el lunes pasado.
A4: =_xlfn.XLOOKUP(E4,Orden_preguntas!$B:$B,Orden_preguntas!$A:$A) -> 3 | B4: {'@1': {'solicitud': '¿Cuál fue el consumo total de la casa durante marzo de 2024?', 'escenario': 'consumo_basico'}} | notas: La solicitud se categoriza en 'consumo_basico' porque el usuario solicita un valor de consumo energético histórico específico (marzo de 2024), lo que cumple con la definición de acceso a datos puntuales o históricos sin análisis comparativo o inferencial. Además, la respuesta esperada es un valor cuantitativo único, alineado con el escenario. | C4: 1 | D4: The model correctly decomposes the single input request into an independent request, accurately reflecting the user's intention to query total household energy consumption for March 2024. No information is invented, and the interpretation aligns perfectly with the Expected Output. Crucially, the request is correctly classified under the 'consumo_basico' scenario, matching the Expected Output. The 'notas' field provides a clear and coherent explanation for this classification, referencing the specific details of the request (historical, specific value, no comparative analysis). | E4: ¿Cuál fue el consumo total de la casa durante marzo de 2024?
A5: =_xlfn.XLOOKUP(E5,Orden_preguntas!$B:$B,Orden_preguntas!$A:$A) -> 4 | B5: {'@1': {'solicitud': 'Quiero saber cuánta energía gastó mi computador hoy.', 'escenario': 'consumo_basico'}} | notas: La solicitud del usuario es una consulta puntual sobre el consumo energético de un dispositivo específico (computador) en un periodo temporal explícito (hoy). Esto coincide con el escenario 'consumo_basico' porque: - La intención principal es acceder a datos históricos (hoy) sin realizar comparaciones o análisis. - Se especifica un periodo temporal explícito. - La respuesta esperada es un valor cuantitativo único. Los otros escenarios no aplican: - No se solicita comparación. - No se busca detección de anomalías o tendencias. - No se requiere estimación o predicción. - La solicitud está claramente relacionada con consumo energético. | C5: 1 | D5: The model correctly decomposes the input into a single intention, accurately reflecting the user's request 'Quiero saber cuánta energía gastó mi computador hoy.' (A1, A2). It correctly classifies this intention under the 'consumo_basico' scenario, which aligns perfectly with the Expected Output (B1). The 'notas' field provides a clear, detailed, and internally consistent explanation for this classification, explicitly justifying the choice based on the request's characteristics and ruling out other scenarios (A4). No implicit intentions were missed, and no information was invented (A3). | E5: Quiero saber cuánta energía gastó mi computador hoy.
A6: =_xlfn.XLOOKUP(E6,Orden_preguntas!$B:$B,Orden_preguntas!$A:$A) -> 5 | B6: {'@1': {'solicitud': '¿Cuánto consumió el aire acondicionado el fin de semana pasado?', 'escenario': 'consumo_basico'}} | notas: La solicitud se categoriza en el escenario 'consumo_basico' porque: 1. El usuario solicita valores de consumo energético históricos específicos (consumo del aire acondicionado). 2. La consulta incluye un periodo de tiempo explícito (el fin de semana pasado). 3. La respuesta esperada es un valor cuantitativo único (el consumo total durante ese periodo). No aplica otros escenarios porque no hay intención de comparación, detección de anomalías, predicción o entrada inadmisible. | C6: 1 | D6: The model correctly decomposes the input into a single intention, which aligns with the expected output. It accurately classifies the intention as 'consumo_basico', matching the expected scenario. Furthermore, the 'notas' field provides clear, consistent, and comprehensive reasoning for the classification, demonstrating strong internal coherence and addressing why other scenarios are not applicable. No information is invented, and no implicit intentions needed to be inferred. | E6: ¿Cuánto consumió el aire acondicionado el fin de semana pasado?
A7: =_xlfn.XLOOKUP(E7,Orden_preguntas!$B:$B,Orden_preguntas!$A:$A) -> 6 | B7: {'@1': {'solicitud': 'Mostrar el consumo energético del ventilador el día de ayer.', 'escenario': 'consumo_basico'}} | notas: La solicitud del usuario es una consulta puntual sobre el consumo energético de un dispositivo específico (ventilador) durante un periodo temporal explícito (ayer). Esto cumple con el escenario 'consumo_basico' ya que no involucra comparaciones, análisis de patrones, predicciones o identificación de anomalías, y la respuesta esperada es un valor cuantitativo único para el período mencionado. | C7: 1 | D7: The model accurately decomposes the single request from the input "Muéstrame el consumo del ventilador el día de ayer" into an independent request without inventing information. The inferred intention, "Mostrar el consumo energético del ventilador el día de ayer," correctly aligns with the expected output's interpretation. Furthermore, the request is correctly classified under the 'consumo_basico' scenario, and the 'notas' field provides a clear and coherent justification for this classification, referencing the specific device and temporal period. | E7: Muéstrame el consumo del ventilador el día de ayer.
A8: =_xlfn.XLOOKUP(E8,Orden_preguntas!$B:$B,Orden_preguntas!$A:$A) -> 7 | B8: {'@1': {'solicitud': 'Consultar el consumo energético del horno el 15 de noviembre.', 'escenario': 'consumo_basico'}} | notas: La solicitud del usuario es una consulta puntual y específica sobre el consumo energético de un dispositivo (horno) en una fecha concreta (15 de noviembre). Esto corresponde al escenario 'consumo_basico' porque: - El usuario solicita un valor histórico (consumo en una fecha específica) - Se especifica explícitamente el periodo temporal (fecha) - La respuesta esperada es un valor cuantitativo único (consumo del día en cuestión) No aplica el escenario 'comparacion_consumos' porque no se solicita comparar con ningún otro dispositivo o periodo. No aplica 'deteccion_anomalias_tendencias' porque no se busca identificar comportamientos anómalos. No aplica 'prediccion_estimacion' porque no se trata de estimar un consumo futuro o hipotético. La solicitud es directamente manejable dentro del sistema. | C8: 1 | D8: The model correctly decomposes the input into a single, independent request without inventing any information (A1, A2). The inferred intention and details in the actual output's request, 'Consultar el consumo energético del horno el 15 de noviembre.', perfectly align with the expected output (A3). Furthermore, the assigned scenario 'consumo_basico' is correct and well-justified in the 'notas' field, which clearly explains why this scenario applies and why others do not, demonstrating strong coherence and accuracy (B1, A4). The detailed explanation in 'notas' is a particular strength. | E8: ¿Cuál fue el consumo energético de mi horno el 15 de noviembre?
A9: =_xlfn.XLOOKUP(E9,Orden_preguntas!$B:$B,Orden_preguntas!$A:$A) -> 8 | B9: {'@1': {'solicitud': 'Dime cuántos kWh consumió mi casa la semana pasada.', 'escenario': 'consumo_basico'}} | notas: La solicitud del usuario es una consulta directa por el consumo energético histórico de su casa en un periodo temporal explícito (la semana pasada). Esto corresponde al escenario 'consumo_basico', ya que la intención principal es acceder a datos históricos sin realizar comparaciones, análisis o estimaciones. El escenario es el adecuado porque la consulta solicita un valor cuantitativo único (el consumo total) para un periodo temporal claramente definido. | C9: 0.9 | D9: The model correctly decomposes the single input request into one independent request (A1) and does not invent any information (A2). The interpretation of the user's intention to query past energy consumption for the house over the last week aligns with the expected output (A3). The assigned scenario 'consumo_basico' is correct and consistent with the expected output, and the 'notas' field provides a clear and coherent justification for this classification, referencing the explicit temporal period and the nature of the query (B1, A4). The only minor difference is the exact phrasing of the 'solicitud' field, but the core interpretation is accurate. | E9: Dime cuántos kWh consumió mi casa la semana pasada.
A10: =_xlfn.XLOOKUP(E10,Orden_preguntas!$B:$B,Orden_preguntas!$A:$A) -> 9 | B10: {'@1': {'solicitud': '¿Cuánto consumió mi nevera durante el mes de enero?', 'escenario': 'consumo_basico'}} | notas: La solicitud del usuario es una consulta por el consumo energético histórico de un dispositivo específico (nevera) durante un periodo temporal explícito (enero). Esto se ajusta al escenario 'consumo_basico' porque la intención principal es acceder a datos históricos de consumo sin hacer comparaciones, análisis de patrones, inferencias ni estimaciones. Además, la respuesta esperada es un valor cuantitativo único o una serie temporal. | C10: 1 | D10: The model correctly decomposes the input into a single intention (A1) without inventing any information (A2). The assigned scenario classification 'consumo_basico' is correct and aligns with the Expected Output (B1). The model also implicitly infers the intention to retrieve historical consumption data for a specific device and period (A3). Furthermore, the 'notas' field provides a clear, detailed, and internally coherent explanation for the classification, referencing specific details from the input like 'nevera' and 'enero' (A4). | E10: ¿Cuánto consumió mi nevera durante el mes de enero?
A11: =_xlfn.XLOOKUP(E11,Orden_preguntas!$B:$B,Orden_preguntas!$A:$A) -> 10 | B11: {'@1': {'solicitud': "La consulta del usuario contiene un término metafórico ('feliz') que no está directamente mapeado a los escenarios de entrada admitidos. No hay suficiente información para segmentar la solicitud en solicitudes autocontenidas y categorizadas.", 'escenario': 'entrada_inadmisible', 'notas': "La intención del usuario involucra un término no estándar ('feliz') que no corresponde directamente a los escenarios de consumo energético. La consulta no se puede mapear a los escenarios disponibles debido a la falta de relación clara con consumo energético."}} | notas: La solicitud del usuario no puede ser categorizada en los escenarios disponibles porque utiliza un término metafórico ('feliz') que no está definido en el dominio del sistema. El sistema está diseñado para tratar consultas relacionadas específicamente con el consumo energético, pero esta expresión es subjetiva y no tiene un equivalente en los parámetros de análisis del sistema. | C11: 1 | D11: The model correctly identifies the input as an 'entrada_inadmisible' due to the metaphorical term 'feliz', aligning perfectly with the Expected Output's classification. It does not invent information and maintains strong internal coherence, with the 'notas' field providing a clear and consistent explanation for the classification. All criteria (A1-A4 and B1) are met, demonstrating accurate decomposition, classification, and reasoning for the input '¿Qué tan feliz estuvo mi casa ayer con el consumo de energía?'. | E11: ¿Qué tan feliz estuvo mi casa ayer con el consumo de energía?
A12: =_xlfn.XLOOKUP(E12,Orden_preguntas!$B:$B,Orden_preguntas!$A:$A) -> 11 | B12: {'@1': {'solicitud': 'Dime el consumo de mi nevera ayer', 'escenario': 'consumo_basico'}, '@2': {'solicitud': 'Dime el consumo de mi lavadora ayer', 'escenario': 'consumo_basico'}} | notas: Para '@1': La solicitud es una consulta puntual de consumo energético histórico (ayer) para un dispositivo específico (nevera), sin requerir comparación, análisis o estimación, por lo que se clasifica en 'consumo_basico'. Para '@2': Similar a '@1', pero para el dispositivo lavadora, también es una consulta puntual de consumo histórico, por lo que se clasifica en 'consumo_basico'. | C12: 1 | D12: El modelo descompone correctamente el input 'Dime el consumo de mi nevera ayer y el consumo de mi lavadora ayer' en dos intenciones individuales e independientes. Clasifica ambas solicitudes como 'consumo_basico', lo cual es consistente con la naturaleza de las consultas de consumo histórico puntual y coincide con el Expected Output. Además, las 'notas' del Actual Output proporcionan un razonamiento claro y coherente para cada clasificación, demostrando una excelente comprensión y aplicación de los criterios de evaluación. | E12: Dime el consumo de mi nevera ayer y el consumo de mi lavadora ayer.
A13: =_xlfn.XLOOKUP(E13,Orden_preguntas!$B:$B,Orden_preguntas!$A:$A) -> 12 | B13: {'@1': {'solicitud': 'Consultar el consumo energético histórico del televisor y del computador el sábado pasado.', 'escenario': 'consumo_basico'}} | notas: La solicitud del usuario es una consulta puntual sobre el consumo energético de dos dispositivos específicos (televisor y computador) en un periodo temporal explícito (sábado pasado). Esto cumple con el escenario 'consumo_basico' porque: 1. La intención principal es acceder a datos históricos de consumo energético 2. No se solicita comparación entre dispositivos o periodos 3. Se requiere un valor cuantitativo único para cada dispositivo en el periodo especificado 4. La consulta es específica y autocontenida | C13: 0.3 | D13: The model failed to correctly decompose the input into all individual, independent intentions (A1). The input asks about the consumption of 'el televisor y el computador', which should result in two distinct requests as shown in the Expected Output. Instead, the Actual Output combined these into a single request. While the scenario classification ('consumo_basico') for the combined request was appropriate and the reasoning in 'notas' was internally coherent (A4), the fundamental failure in decomposition places the response in the lowest score range. | E13: ¿Cuánto consumieron el televisor y el computador el sábado pasado?
... A51: =_xlfn.XLOOKUP(E51,Orden_preguntas!$B:$B,Orden_preguntas!$A:$A) -> 50 | B51: {'@1': {'solicitud': 'Consultar el consumo energético de la nevera el día ayer', 'escenario': 'consumo_basico'}, '@2': {'solicitud': 'Comparar el consumo energético de la nevera con el de la lavadora', 'escenario': 'comparacion_consumos'}, '@3': {'solicitud': 'Estimar si el ahorro derivado de la comparación anterior permitiría cubrir los gastos del viaje', 'escenario': 'prediccion_estimacion'}} | notas: La solicitud original contiene tres intenciones principales, cada una con su propio escenario: 1. "Dime el consumo de mi nevera ayer": Esta es una solicitud clara de datos históricos específicos (ayer), por lo que se asigna a 'consumo_basico'. 2. "compárala con la lavadora": Esto indica una comparación entre dos dispositivos (nevera y lavadora), que corresponde al escenario 'comparacion_consumos'. 3. "y dime si con eso ya puedo ahorrar para irme de viaje": Aquí, el usuario busca determinar si el consumo más bajo (quizás la nevera) genera un ahorro suficiente para un viaje. Esto requiere una estimación basada en los datos históricos, por lo que se asigna a 'prediccion_estimacion'. El sistema no conoce el presupuesto del viaje, pero el usuario quiere una inferencia a partir de los datos de consumo. | C51: 0.6 | D51: The model correctly decomposes the input into three distinct intentions and maintains internal coherence in its reasoning, aligning with A1, A2, A3, and A4. It accurately classifies the first two intentions, 'Consultar el consumo energético de la nevera el día ayer' as 'consumo_basico' and 'Comparar el consumo energético de la nevera con el de la lavadora' as 'comparacion_consumos'. However, it incorrectly classifies the third intention, 'Estimar si el ahorro derivado de la comparación anterior permitiría cubrir los gastos del viaje', as 'prediccion_estimacion' (B1 incorrect), whereas the Expected Output correctly identifies it as 'entrada_inadmisible' because it's outside the system's domain. | E51: Dime el consumo de mi nevera ayer, compárala con la lavadora y dime si con eso ya puedo ahorrar para irme de viaje.

Sheet Xiaomi_mimoV2_flash_15b_309b
A1: ID_PREGUNTA | B1: Respuesta_Modelo | C1: Puntaje_Calidad | D1: Razon_del_Juez | E1: Pregunta | F1: revision_humana
A2: =_xlfn.XLOOKUP(E2,Orden_preguntas!$B:$B,Orden_preguntas!$A:$A) -> 1 | B2: {'@1': {'solicitud': 'Consultar el consumo energético del televisor específico durante el periodo de la noche del día anterior.', 'escenario': 'consumo_basico'}} | notas: La solicitud del usuario pregunta explícitamente por valores de consumo energético ("cuánto consumió") para un dispositivo específico ("mi televisor") dentro de un intervalo temporal claro ("ayer en la noche"). No se piden comparaciones, inferencias de patrones, ni predicciones futuras, por lo que encaja perfectamente en la definición de 'consumo_basico'. | C2: 1 | D2: The model correctly decomposes the single input request into an independent request (A1) without inventing information (A2). The inferred intention in the 'solicitud' field, 'Consultar el consumo energético del televisor específico durante el periodo de la noche del día anterior.', accurately interprets the input '¿Cuánto consumió mi televisor ayer en la noche?' and aligns with the expected output's interpretation (A3). The assigned scenario 'consumo_basico' is correct for a direct query of historical consumption for a specific device and period (B1). Furthermore, the 'notas' field provides a clear and coherent explanation for this classification, referencing specific details from the input (A4). | E2: ¿Cuánto consumió mi televisor ayer en la noche?
A3: =_xlfn.XLOOKUP(E3,Orden_preguntas!$B:$B,Orden_preguntas!$A:$A) -> 2 | B3: {'@1': {'solicitud': 'Dime el consumo de mi lavadora el lunes pasado.', 'escenario': 'consumo_basico'}} | notas: La solicitud del usuario es "Dime el consumo de mi lavadora el lunes pasado". 1. **Análisis de intención:** El usuario pide un valor de consumo específico ("consumo de mi lavadora") para una fecha concreta ("el lunes pasado"). No solicita comparar, predecir ni detectar anomalías, solo consultar un dato histórico. 2. **Verificación de escenarios:** * **`consumo_basico`:** Se solicita un valor de consumo energético histórico para un dispositivo específico ("lavadora") dentro de un intervalo temporal explícito ("lunes pasado"). La respuesta esperada es un valor cuantitativo. * **`comparacion_consumos`:** El usuario no compara dos o más consumos. * **`deteccion_anomalias_tendencias`:** El usuario no menciona picos, anomalías ni tendencias. * **`prediccion_estimacion`:** El usuario no solicita estimaciones futuras ni escenarios hipotéticos. * **`entrada_inadmisible`:** La consulta está relacionada con el consumo energético del hogar y es clara. 3. **Conclusión:** La solicitud encaja perfectamente en la definición de `consumo_basico` ("Solicitudes cuya intención principal es consultar valores de consumo energético ya registrados... dentro de un intervalo temporal explícito o claramente inferible"). | C3: 1 | D3: The model correctly decomposes the input 'Dime el consumo de mi lavadora el lunes pasado' into a single intention (A1) without inventing information (A2). It accurately classifies this request as 'consumo_basico' (B1), which aligns perfectly with the Expected Output. The 'notas' field provides a clear, detailed, and internally coherent (A4) justification for this classification, thoroughly explaining why 'consumo_basico' is appropriate and ruling out other scenarios. No implicit intentions needed to be inferred (A3). | E3: Dime el consumo de mi lavadora el lunes pasado.
A4: =_xlfn.XLOOKUP(E4,Orden_preguntas!$B:$B,Orden_preguntas!$A:$A) -> 3 | B4: {'@1': {'solicitud': 'Consulta el consumo total de energía eléctrica de la casa durante el mes de marzo de 2024.', 'escenario': 'consumo_basico'}} | notas: La solicitud del usuario se refiere a la consulta de un valor de consumo energético histórico ("consumo total de la casa") para un periodo de tiempo explícito ("marzo de 2024"). La intención es acceder a un dato cuantitativo específico sin realizar comparaciones, análisis de patrones o estimaciones futuras. Por lo tanto, se clasifica bajo el escenario 'consumo_basico'. | C4: 0.9 | D4: The model correctly decomposes the input '¿Cuál fue el consumo total de la casa durante marzo de 2024?' into a single, independent intention, aligning with A1. It does not invent information (A2), and the inferred intention 'Consulta el consumo total de energía eléctrica de la casa durante el mes de marzo de 2024' is accurate and consistent with the input. The scenario classification 'consumo_basico' is correct according to B1, as it's a direct query for historical consumption. The 'notas' field provides clear and consistent reasoning for the classification, demonstrating strong internal coherence (A4). The slight difference in phrasing of the 'solicitud' compared to the Expected Output is minor and does not detract from its correctness or completeness. | E4: ¿Cuál fue el consumo total de la casa durante marzo de 2024?
A5: =_xlfn.XLOOKUP(E5,Orden_preguntas!$B:$B,Orden_preguntas!$A:$A) -> 4 | B5: {'@1': {'solicitud': 'Consultar el consumo energético total del dispositivo computador para el día de hoy.', 'escenario': 'consumo_basico'}} | notas: La solicitud del usuario busca un valor específico de consumo energético ("cuánta energía gastó") para un dispositivo particular ("mi computador") dentro de un intervalo de tiempo claramente definido ("hoy"). No se solicita comparar con otros dispositivos ni se buscan patrones o anomalías, por lo que la intención se alinea directamente con la consulta de datos históricos puntuales. El sistema admite este tipo de solicitudes bajo el escenario 'consumo_basico', descrito para consultas de valores registrados con un intervalo temporal explícito. | C5: 1 | D5: The model accurately decomposes the input 'Quiero saber cuánta energía gastó mi computador hoy' into a single, independent intention, aligning perfectly with the Expected Output (A1, A2). It correctly infers the explicit request for energy consumption of a specific device for today (A3). The scenario classification as 'consumo_basico' is correct and matches the Expected Output (B1). Furthermore, the 'notas' field provides a clear and consistent justification for both the identified request and its classification, demonstrating strong internal coherence (A4). | E5: Quiero saber cuánta energía gastó mi computador hoy.
A6: =_xlfn.XLOOKUP(E6,Orden_preguntas!$B:$B,Orden_preguntas!$A:$A) -> 5 | B6: {'@1': {'solicitud': 'Consultar el consumo energético del aire acondicionado durante el fin de semana pasado (sábado y domingo anterior a la fecha actual).', 'escenario': 'consumo_basico'}} | notas: La consulta del usuario solicita valores de consumo energético ya registrados para un dispositivo específico (aire acondicionado) dentro de un intervalo temporal explícito y ya pasado ("fin de semana pasado"). Se clasificó en el escenario **consumo_basico** porque: 1. La intención es acceder a datos puntuales o históricos ("Cuánto consumió"). 2. Incluye un periodo de tiempo claramente inferible (el fin de semana anterior). 3. No solicita comparar con otros periodos o dispositivos, ni identificar anomalías, ni realizar predicciones futuras; simplemente solicita el valor del consumo registrado. | C6: 1 | D6: The model correctly decomposes the input '¿Cuánto consumió el aire acondicionado el fin de semana pasado?' into a single, independent intention. It accurately infers the implicit temporal context of 'fin de semana pasado' as the previous Saturday and Sunday without inventing information. The scenario classification 'consumo_basico' is correct and aligns with the Expected Output. Furthermore, the 'notas' field demonstrates strong internal coherence, providing clear and consistent reasoning for both the identified request and its classification, fulfilling all criteria for a top score. | E6: ¿Cuánto consumió el aire acondicionado el fin de semana pasado?
A7: =_xlfn.XLOOKUP(E7,Orden_preguntas!$B:$B,Orden_preguntas!$A:$A) -> 6 | B7: {'@1': {'solicitud': 'Proporciona el consumo energético del ventilador correspondiente al día completo del día anterior al actual.', 'escenario': 'consumo_basico'}} | notas: El usuario solicita explícitamente el consumo energético de un dispositivo específico ("el ventilador") para un periodo de tiempo determinado ("el día de ayer"). Esta consulta se ajusta perfectamente al escenario 'consumo_basico', ya que el objetivo es acceder a datos históricos cuantitativos de consumo para un intervalo temporal definido, sin solicitar comparaciones, análisis de patrones, estimaciones futuras ni detección de anomalías. | C7: 1 | D7: The model correctly decomposes the input 'Muéstrame el consumo del ventilador el día de ayer' into a single, independent intention. It accurately rephrases the request as 'Proporciona el consumo energético del ventilador correspondiente al día completo del día anterior al actual' without inventing information. The assigned scenario classification 'consumo_basico' is correct and aligns with the Expected Output. Additionally, the 'notas' field provides a clear and consistent explanation for this classification, demonstrating strong internal coherence. | E7: Muéstrame el consumo del ventilador el día de ayer.
A8: =_xlfn.XLOOKUP(E8,Orden_preguntas!$B:$B,Orden_preguntas!$A:$A) -> 7 | B8: {'@1': {'solicitud': 'Consultar el consumo energético registrado del horno durante el día 15 de noviembre de 2023.', 'escenario': 'consumo_basico'}} | notas: La solicitud del usuario pregunta específicamente por los valores de consumo energético históricos de un dispositivo (horno) para un intervalo temporal explícito (15 de noviembre). Esto coincide directamente con el escenario 'consumo_basico', el cual se utiliza para consultas puntuales de datos históricos sin análisis comparativo ni inferencias futuras. | C8: 0.9 | D8: The model correctly decomposed the input into a single request, accurately interpreting the user's intention to query historical energy consumption for the oven on November 15th. It assigned the correct 'consumo_basico' scenario, aligning with the expected output. The 'notas' field provided a clear and coherent justification for the classification. Although the 'solicitud' and 'notas' were slightly more verbose than the expected output, they did not invent information or misinterpret the input, fulfilling all A1-A4 and B1 criteria. | E8: ¿Cuál fue el consumo energético de mi horno el 15 de noviembre?
A9: =_xlfn.XLOOKUP(E9,Orden_preguntas!$B:$B,Orden_preguntas!$A:$A) -> 8 | B9: {'@1': {'solicitud': 'Consulta el consumo energético total (en kWh) registrado para la vivienda completa durante el periodo de tiempo correspondiente a la semana pasada.', 'escenario': 'consumo_basico'}} | notas: La solicitud del usuario es "Dime cuántos kWh consumió mi casa la semana pasada.". 1. **Análisis de la Intención**: El usuario pide un valor numérico específico ("cuántos kWh") para un periodo de tiempo definido ("la semana pasada"). La palabra clave "consumió" indica una acción pasada, lo que implica que se requiere acceder a datos históricos registrados. 2. **Evaluación de Escenarios**: * **`consumo_basico`**: El escenario de `consumo_basico` se define para solicitudes cuya intención es "consultar valores de consumo energético ya registrados" dentro de un "intervalo temporal explícito o claramente inferible". La respuesta esperada es un "valor cuantitativo único". La solicitud del usuario encaja perfectamente en esta descripción. "La semana pasada" es un intervalo temporal inferible, y se solicita un valor cuantitativo (kWh). * **`comparacion_consumos`**: No se aplica, ya que no se solicita comparar con otro dispositivo, zona o periodo distinto. * **`deteccion_anomalias_tendencias`**: No se aplica, ya que el usuario no menciona anomalías, picos ni tendencias; solo busca un dato total. * **`prediccion_estimacion`**: No se aplica, ya que se refiere a consumo pasado (histórico), no a estimaciones futuras. * **`entrada_inadmisible`**: No se aplica, la solicitud está claramente dentro del dominio del consumo energético del hogar. 3. **Conclusión**: La solicitud se categoriza bajo el escenario **`consumo_basico`**. | C9: 0.9 | D9: The model correctly decomposes the input into a single request and accurately interprets the user's intention to query total energy consumption for 'la semana pasada' (A1, A2, A3). The assigned scenario 'consumo_basico' is correct and aligns with the expected output, demonstrating proper classification based on the context (B1). The 'solicitud' field is very similar to the expected output, showing strong alignment. The 'notas' field in the actual output, while coherent, is less descriptive than the expected output's notes, but it does not introduce incoherence or incorrect information (A4). | E9: Dime cuántos kWh consumió mi casa la semana pasada.
A10: =_xlfn.XLOOKUP(E10,Orden_preguntas!$B:$B,Orden_preguntas!$A:$A) -> 9 | B10: {'@1': {'solicitud': 'Consulta del consumo energético total de la nevera durante el mes de enero.', 'escenario': 'consumo_basico'}} | notas: La solicitud del usuario es '¿Cuánto consumió mi nevera durante el mes de enero?'. Esta consulta solicita un valor cuantitativo histórico (el consumo total) para un dispositivo específico (la nevera) dentro de un intervalo temporal explícito (el mes de enero). No solicita comparaciones, análisis de patrones ni predicciones, simplemente el dato registrado. Por lo tanto, se categoriza bajo el escenario 'consumo_basico', ya que encaja perfectamente con la descripción de consultas de valores de consumo energético ya registrados con un intervalo temporal definido. | C10: 1 | D10: The model correctly decomposes the single user request from the input '¿Cuánto consumió mi nevera durante el mes de enero?' into an individual request. It accurately infers the intention as 'Consulta del consumo energético total de la nevera durante el mes de enero.', which aligns perfectly with the expected output's interpretation. No information is invented. The assigned scenario 'consumo_basico' is correct and matches the expected output. Furthermore, the 'notas' field provides a clear, coherent, and detailed justification for the classification, demonstrating a strong understanding of the request's nature. | E10: ¿Cuánto consumió mi nevera durante el mes de enero?
A11: =_xlfn.XLOOKUP(E11,Orden_preguntas!$B:$B,Orden_preguntas!$A:$A) -> 10 | B11: {'@1': {'solicitud': 'Consultar el consumo de energía total de la casa durante el día de ayer.', 'escenario': 'consumo_basico'}} | notas: La solicitud del usuario pregunta "¿Qué tan feliz estuvo mi casa ayer con el consumo de energía?". El uso de la palabra "feliz" es una metáfora o antropomorfismo que el sistema debe interpretar como una consulta sobre la adecuación o el nivel de consumo (probablemente bajo o eficiente). Dado que la consulta se refiere explícitamente al consumo de energía de "mi casa" y menciona un tiempo específico ("ayer"), esta solicitud encaja perfectamente en el escenario de **consumo_basico**. La intención principal es consultar un valor histórico registrado dentro de un intervalo temporal claro, sin solicitar comparaciones, detección de anomalías ni predicciones futuras. La respuesta esperada es un valor cuantitativo del consumo del día anterior. | C11: 0.2 | D11: The model fails to correctly interpret the user's input, transforming a metaphorical and non-technical query ("¿Qué tan feliz estuvo mi casa ayer con el consumo de energía?") into an actionable technical request ('Consultar el consumo de energía total de la casa durante el día de ayer.'). This constitutes inventing information (A2) not deducible as a valid system action, as the Expected Output explicitly classifies it as 'entrada_inadmisible'. Consequently, the interpretation (A3) and the scenario assignment ('consumo_basico' instead of 'entrada_inadmisible') are incorrect (B1), indicating insufficient semantic quality. | E11: ¿Qué tan feliz estuvo mi casa ayer con el consumo de energía?
A12: =_xlfn.XLOOKUP(E12,Orden_preguntas!$B:$B,Orden_preguntas!$A:$A) -> 11 | B12: {'@1': {'solicitud': 'Consultar el consumo energético de la nevera durante el día de ayer.', 'escenario': 'consumo_basico'}, '@2': {'solicitud': 'Consultar el consumo energético de la lavadora durante el día de ayer.', 'escenario': 'consumo_basico'}} | notas: Se han identificado dos solicitudes independientes en el prompt del usuario. 1. **Solicitud 1 (@1)**: "consumo de mi nevera ayer". - **Intención**: Consultar un valor cuantitativo (consumo) de un dispositivo específico (nevera) en un periodo temporal explícito (ayer). - **Escenario elegido**: `consumo_basico`. - **Razonamiento**: La consulta pide un valor histórico de consumo sin realizar comparaciones, análisis de patrones ni estimaciones futuras. Cumple con los criterios de la descripción del escenario "consultar valores de consumo energético ya registrados" y "respuesta esperada es un valor cuantitativo". 2. **Solicitud 2 (@2)**: "consumo de mi lavadora ayer". - **Intención**: Consultar un valor cuantitativo (consumo) de un dispositivo específico (lavadora) en un periodo temporal explícito (ayer). - **Escenario elegido**: `consumo_basico`. - **Razonamiento**: Idéntico al anterior. Se solicita un dato histórico puntual sin análisis comparativo o inferencial adicional. Ambas solicitudes son autocontenidas y se clasifican correctamente en el escenario `consumo_basico` ya que su objetivo es obtener datos históricos específicos. | C12: 1 | D12: The model correctly decomposes the input into two independent intentions for the fridge and washing machine consumption (A1), without inventing any information (A2). Both intentions are accurately classified as 'consumo_basico' (B1), matching the Expected Output. The 'notas' field provides clear and consistent reasoning for these classifications, demonstrating strong internal coherence (A4) by explaining why each request fits the 'consumo_basico' scenario. | E12: Dime el consumo de mi nevera ayer y el consumo de mi lavadora ayer.
A13: =_xlfn.XLOOKUP(E13,Orden_preguntas!$B:$B,Orden_preguntas!$A:$A) -> 12 | B13: {'@1': {'solicitud': 'Consultar el consumo energético del televisor durante el sábado pasado.', 'escenario': 'consumo_basico'}, '@2': {'solicitud': 'Consultar el consumo energético del computador durante el sábado pasado.', 'escenario': 'consumo_basico'}} | notas: Se identificó que el usuario solicita valores de consumo energético históricos para dos dispositivos específicos (televisor y computador) en un periodo de tiempo explícito ("sábado pasado"). Dado que la intención principal es acceder a datos puntuales sin realizar comparaciones ni análisis complejos, se categoriza bajo el escenario 'consumo_basico'. Se separa en dos solicitudes independientes (@1 y @2) porque cada una es autocontenida y corresponde a un dispositivo distinto. | C13: 1 | D13: The model correctly decomposes the input into two independent intentions for the television and computer (A1). It accurately infers the implicit intention of 'consumo energético' and does not invent any information (A2, A3). Each intention is correctly classified under the 'consumo_basico' scenario, aligning with the Expected Output (B1). The 'notas' field provides a clear and consistent explanation for the decomposition and classification, demonstrating strong internal coherence (A4). The output perfectly matches the expected behavior for the input '¿Cuánto consumieron el televisor y el computador el sábado pasado?' | E13: ¿Cuánto consumieron el televisor y el computador el sábado pasado?
... A16: =_xlfn.XLOOKUP(E16,Orden_preguntas!$B:$B,Orden_preguntas!$A:$A) -> 15 | B16: {'@1': {'solicitud': 'Consulta el consumo energético del ventilador para la semana actual (desde el inicio de la semana en curso hasta el día actual).', 'escenario': 'consumo_basico'}, '@2': {'solicitud': 'Consulta el consumo energético de la lavadora para la semana anterior (completa, desde el lunes hasta el domingo de la semana previa).', 'escenario': 'consumo_basico'}} | notas: El prompt del usuario contiene dos solicitudes explícitas que son independientes entre sí: 1. "consumo del ventilador esta semana": Se refiere a obtener datos históricos de consumo para un dispositivo específico (ventilador) en un intervalo temporal definido (esta semana). No implica comparaciones, análisis de patrones ni estimaciones futuras, por lo que se clasifica bajo el escenario 'consumo_basico'. 2. "el de la lavadora la semana pasada": También es una consulta de datos históricos para un dispositivo específico (lavadora) en un intervalo temporal claro (semana anterior). Al igual que la anterior, se centra únicamente en la retrievación de valores cuantitativos sin análisis adicional, clasificándose también como 'consumo_basico'. Se generan dos solicitudes separadas (@1 y @2) ya que cada una requiere un foco de datos distinto y deben ser autocontenidas, garantizando que el sistema pueda procesar cada consulta de forma aislada. | C16: 0.9 | D16: The model correctly decomposes the input into two independent requests, aligning with A1. It does not invent information (A2), but rather provides a slightly more detailed, yet accurate, interpretation of the timeframes ('esta semana' and 'la semana pasada') which is a reasonable inference. The inferred intentions and details in the decomposed requests closely match the Expected Output (A3). Both requests are correctly classified under the 'consumo_basico' scenario, consistent with the Expected Output and the nature of the queries (B1). The 'notas' field is clear, coherent, and provides a good explanation for the decomposition and scenario assignment (A4). The slight elaboration on the timeframes in the 'solicitud' field, while not strictly identical to the Expected Output's brevity, is a valid and helpful clarification rather than a shortcoming. | E16: Dime el consumo del ventilador esta semana y el de la lavadora la semana pasada.
A17: =_xlfn.XLOOKUP(E17,Orden_preguntas!$B:$B,Orden_preguntas!$A:$A) -> 16 | B17: {'@1': {'solicitud': 'Proporciona el consumo energético de mi PC, mi monitor y mi router correspondiente al día de ayer.', 'escenario': 'consumo_basico'}} | notas: La solicitud del usuario ("¿Cuánta energía gastaron mi PC, mi monitor y mi router ayer?") busca acceder a datos históricos específicos de consumo energético para tres dispositivos concretos en un intervalo temporal definido ("ayer"). No solicita comparaciones entre ellos ni análisis de tendencias, simplemente los valores cuantitativos individuales. Por lo tanto, se encaja en el escenario de 'consumo_basico', ya que el objetivo es consultar valores registrados sin realizar comparaciones analíticas, análisis de patrones ni inferencias. | C17: 0.8 | D17: The Actual Output fails to correctly decompose the Input into all individual, independent intentions (A1). The Input asks about three distinct devices (PC, monitor, router), which the Expected Output correctly breaks down into three separate 'consumo_basico' requests. However, the Actual Output combines these into a single request, indicating a significant shortcoming in identifying independent intentions. While the classification of the single identified intention as 'consumo_basico' is correct and the 'notas' are internally consistent with this single request, the fundamental failure in decomposition places it in the 0-4 range of the rubric. | E17: ¿Cuánta energía gastaron mi PC, mi monitor y mi router ayer? | F17: Aunque efectivamenet no descompuso la solicitud por cada dispositivo por aparte, el sistema está capacitado para recibir ese tipo de solicitud. Nueva calificación: 0.8
A18: =_xlfn.XLOOKUP(E18,Orden_preguntas!$B:$B,Orden_preguntas!$A:$A) -> 17 | B18: {'@1': {'solicitud': 'Muéstrame el consumo del horno en enero.', 'escenario': 'consumo_basico'}, '@2': {'solicitud': 'Muéstrame el consumo del horno en febrero.', 'escenario': 'consumo_basico'}} | notas: Se identifican dos solicitudes independientes referentes al consumo de un dispositivo específico (el horno) en dos periodos de tiempo distintos (enero y febrero). Ambas solicitudes buscan acceder a datos históricos de consumo energético para un intervalo temporal explícito, sin requerir comparaciones entre ellos. Por lo tanto, se categorizan bajo el escenario 'consumo_basico'. | C18: 0.7 | D18: The model correctly decomposes the input 'Muéstrame el consumo del horno en enero y en febrero' into two independent intentions (A1) and does not invent information (A2). It also correctly classifies both requests under the 'consumo_basico' scenario (B1), aligning with the Expected Output. The reasoning provided in the 'notas' field is clear and internally consistent with its identified requests and classifications (A4). However, the model fails to adequately infer implicit intentions (A3) as its 'notas' explicitly states 'sin requerir comparaciones entre ellos', which contradicts the Expected Output's 'notas' indicating 'comparación implícita entre periodos'. This specific shortcoming prevents a score in the 8-10 range, despite strong performance on other criteria. | E18: Muéstrame el consumo del horno en enero y en febrero.
